Workbook

Sheet P&L Dashboard
A1: VELOCITYMATCH - P&L DASHBOARD
A2: 24-Month Financial Performance
A5: Month | B5: Total Revenue | C5: Matching Engine | D5: Placements | E5: Add-ons | F5: COGS | G5: Gross Profit | H5: OpEx | I5: Net Profit | J5: Gross Margin % | K5: Net Margin %
A6: M1 | B6: ='P&L'!C33 -> 25252 | C6: ='P&L'!C29 -> 1196 | D6: ='P&L'!C30 -> 24000 | E6: ='P&L'!C31 -> 0 | F6: ='P&L'!C37 -> 1360 | G6: ='P&L'!C38 -> 23892 | H6: ='P&L'!C40 -> 18989.5 | I6: ='P&L'!C41 -> 4902.5 | J6: ='P&L'!C39 -> 0.94614288 | K6: ='P&L'!C42 -> 0.19414304
A7: M2 | B7: ='P&L'!D33 -> 31565 | C7: ='P&L'!D29 -> 1495 | D7: ='P&L'!D30 -> 30000 | E7: ='P&L'!D31 -> 0 | F7: ='P&L'!D37 -> 1700 | G7: ='P&L'!D38 -> 29865 | H7: ='P&L'!D40 -> 18989.5 | I7: ='P&L'!D41 -> 10875.5 | J7: ='P&L'!D39 -> 0.94614288 | K7: ='P&L'!D42 -> 0.34454301
A8: M3 | B8: ='P&L'!E33 -> 37878 | C8: ='P&L'!E29 -> 1794 | D8: ='P&L'!E30 -> 36000 | E8: ='P&L'!E31 -> 0 | F8: ='P&L'!E37 -> 2040 | G8: ='P&L'!E38 -> 35838 | H8: ='P&L'!E40 -> 23793.667 | I8: ='P&L'!E41 -> 12044.333 | J8: ='P&L'!E39 -> 0.94614288 | K8: ='P&L'!E42 -> 0.31797701
A9: M4 | B9: ='P&L'!F33 -> 45871 | C9: ='P&L'!F29 -> 2093 | D9: ='P&L'!F30 -> 42000 | E9: ='P&L'!F31 -> 1680 | F9: ='P&L'!F37 -> 2548 | G9: ='P&L'!F38 -> 43323 | H9: ='P&L'!F40 -> 23793.667 | I9: ='P&L'!F41 -> 19529.333 | J9: ='P&L'!F39 -> 0.94445292 | K9: ='P&L'!F42 -> 0.42574466
A10: M5 | B10: ='P&L'!G33 -> 52424 | C10: ='P&L'!G29 -> 2392 | D10: ='P&L'!G30 -> 48000 | E10: ='P&L'!G31 -> 1920 | F10: ='P&L'!G37 -> 2912 | G10: ='P&L'!G38 -> 49512 | H10: ='P&L'!G40 -> 23793.667 | I10: ='P&L'!G41 -> 25718.333 | J10: ='P&L'!G39 -> 0.94445292 | K10: ='P&L'!G42 -> 0.49058319
A11: M6 | B11: ='P&L'!H33 -> 58977 | C11: ='P&L'!H29 -> 2691 | D11: ='P&L'!H30 -> 54000 | E11: ='P&L'!H31 -> 2160 | F11: ='P&L'!H37 -> 3276 | G11: ='P&L'!H38 -> 55701 | H11: ='P&L'!H40 -> 23793.667 | I11: ='P&L'!H41 -> 31907.333 | J11: ='P&L'!H39 -> 0.94445292 | K11: ='P&L'!H42 -> 0.54101316
A12: M7 | B12: ='P&L'!I33 -> 65530 | C12: ='P&L'!I29 -> 2990 | D12: ='P&L'!I30 -> 60000 | E12: ='P&L'!I31 -> 2400 | F12: ='P&L'!I37 -> 3640 | G12: ='P&L'!I38 -> 61890 | H12: ='P&L'!I40 -> 25177.267 | I12: ='P&L'!I41 -> 36712.733 | J12: ='P&L'!I39 -> 0.94445292 | K12: ='P&L'!I42 -> 0.56024315
A13: M8 | B13: ='P&L'!J33 -> 72083 | C13: ='P&L'!J29 -> 3289 | D13: ='P&L'!J30 -> 66000 | E13: ='P&L'!J31 -> 2640 | F13: ='P&L'!J37 -> 4004 | G13: ='P&L'!J38 -> 68079 | H13: ='P&L'!J40 -> 25177.267 | I13: ='P&L'!J41 -> 42901.733 | J13: ='P&L'!J39 -> 0.94445292 | K13: ='P&L'!J42 -> 0.59517131
A14: M9 | B14: ='P&L'!K33 -> 78636 | C14: ='P&L'!K29 -> 3588 | D14: ='P&L'!K30 -> 72000 | E14: ='P&L'!K31 -> 2880 | F14: ='P&L'!K37 -> 4368 | G14: ='P&L'!K38 -> 74268 | H14: ='P&L'!K40 -> 25177.267 | I14: ='P&L'!K41 -> 49090.733 | J14: ='P&L'!K39 -> 0.94445292 | K14: ='P&L'!K42 -> 0.62427811
A15: M10 | B15: ='P&L'!L33 -> 85189 | C15: ='P&L'!L29 -> 3887 | D15: ='P&L'!L30 -> 78000 | E15: ='P&L'!L31 -> 3120 | F15: ='P&L'!L37 -> 4732 | G15: ='P&L'!L38 -> 80457 | H15: ='P&L'!L40 -> 25177.267 | I15: ='P&L'!L41 -> 55279.733 | J15: ='P&L'!L39 -> 0.94445292 | K15: ='P&L'!L42 -> 0.64890694
A16: M11 | B16: ='P&L'!M33 -> 91742 | C16: ='P&L'!M29 -> 4186 | D16: ='P&L'!M30 -> 84000 | E16: ='P&L'!M31 -> 3360 | F16: ='P&L'!M37 -> 5096 | G16: ='P&L'!M38 -> 86646 | H16: ='P&L'!M40 -> 25177.267 | I16: ='P&L'!M41 -> 61468.733 | J16: ='P&L'!M39 -> 0.94445292 | K16: ='P&L'!M42 -> 0.67001737
A17: M12 | B17: ='P&L'!N33 -> 98295 | C17: ='P&L'!N29 -> 4485 | D17: ='P&L'!N30 -> 90000 | E17: ='P&L'!N31 -> 3600 | F17: ='P&L'!N37 -> 5460 | G17: ='P&L'!N38 -> 92835 | H17: ='P&L'!N40 -> 25177.267 | I17: ='P&L'!N41 -> 67657.733 | J17: ='P&L'!N39 -> 0.94445292 | K17: ='P&L'!N42 -> 0.68831307
A18: M13 | B18: ='P&L'!O33 -> 124507 | C18: ='P&L'!O29 -> 5681 | D18: ='P&L'!O30 -> 114000 | E18: ='P&L'!O31 -> 4560 | F18: ='P&L'!O37 -> 6916 | G18: ='P&L'!O38 -> 117591 | H18: ='P&L'!O40 -> 27694.993 | I18: ='P&L'!O41 -> 89896.007 | J18: ='P&L'!O39 -> 0.94445292 | K18: ='P&L'!O42 -> 0.72201568
A19: M14 | B19: ='P&L'!P33 -> 157272 | C19: ='P&L'!P29 -> 7176 | D19: ='P&L'!P30 -> 144000 | E19: ='P&L'!P31 -> 5760 | F19: ='P&L'!P37 -> 8736 | G19: ='P&L'!P38 -> 148536 | H19: ='P&L'!P40 -> 27694.993 | I19: ='P&L'!P41 -> 120841.01 | J19: ='P&L'!P39 -> 0.94445292 | K19: ='P&L'!P42 -> 0.76835677
A20: M15 | B20: ='P&L'!Q33 -> 196590 | C20: ='P&L'!Q29 -> 8970 | D20: ='P&L'!Q30 -> 180000 | E20: ='P&L'!Q31 -> 7200 | F20: ='P&L'!Q37 -> 10920 | G20: ='P&L'!Q38 -> 185670 | H20: ='P&L'!Q40 -> 27694.993 | I20: ='P&L'!Q41 -> 157975.01 | J20: ='P&L'!Q39 -> 0.94445292 | K20: ='P&L'!Q42 -> 0.803576
A21: M16 | B21: ='P&L'!R33 -> 249014 | C21: ='P&L'!R29 -> 11362 | D21: ='P&L'!R30 -> 228000 | E21: ='P&L'!R31 -> 9120 | F21: ='P&L'!R37 -> 13832 | G21: ='P&L'!R38 -> 235182 | H21: ='P&L'!R40 -> 27694.993 | I21: ='P&L'!R41 -> 207487.01 | J21: ='P&L'!R39 -> 0.94445292 | K21: ='P&L'!R42 -> 0.8332343
A22: M17 | B22: ='P&L'!S33 -> 307991 | C22: ='P&L'!S29 -> 14053 | D22: ='P&L'!S30 -> 282000 | E22: ='P&L'!S31 -> 11280 | F22: ='P&L'!S37 -> 17108 | G22: ='P&L'!S38 -> 290883 | H22: ='P&L'!S40 -> 27694.993 | I22: ='P&L'!S41 -> 263188.01 | J22: ='P&L'!S39 -> 0.94445292 | K22: ='P&L'!S42 -> 0.85453149
A23: M18 | B23: ='P&L'!T33 -> 386627 | C23: ='P&L'!T29 -> 17641 | D23: ='P&L'!T30 -> 354000 | E23: ='P&L'!T31 -> 14160 | F23: ='P&L'!T37 -> 21476 | G23: ='P&L'!T38 -> 365151 | H23: ='P&L'!T40 -> 27694.993 | I23: ='P&L'!T41 -> 337456.01 | J23: ='P&L'!T39 -> 0.94445292 | K23: ='P&L'!T42 -> 0.87282059
A24: M19 | B24: ='P&L'!U33 -> 491475 | C24: ='P&L'!U29 -> 22425 | D24: ='P&L'!U30 -> 450000 | E24: ='P&L'!U31 -> 18000 | F24: ='P&L'!U37 -> 27300 | G24: ='P&L'!U38 -> 464175 | H24: ='P&L'!U40 -> 27694.993 | I24: ='P&L'!U41 -> 436480.01 | J24: ='P&L'!U39 -> 0.94445292 | K24: ='P&L'!U42 -> 0.88810216
A25: M20 | B25: ='P&L'!V33 -> 622535 | C25: ='P&L'!V29 -> 28405 | D25: ='P&L'!V30 -> 570000 | E25: ='P&L'!V31 -> 22800 | F25: ='P&L'!V37 -> 34580 | G25: ='P&L'!V38 -> 587955 | H25: ='P&L'!V40 -> 27694.993 | I25: ='P&L'!V41 -> 560260.01 | J25: ='P&L'!V39 -> 0.94445292 | K25: ='P&L'!V42 -> 0.89996547
A26: M21 | B26: ='P&L'!W33 -> 786360 | C26: ='P&L'!W29 -> 35880 | D26: ='P&L'!W30 -> 720000 | E26: ='P&L'!W31 -> 28800 | F26: ='P&L'!W37 -> 43680 | G26: ='P&L'!W38 -> 742680 | H26: ='P&L'!W40 -> 27694.993 | I26: ='P&L'!W41 -> 714985.01 | J26: ='P&L'!W39 -> 0.94445292 | K26: ='P&L'!W42 -> 0.90923369
A27: M22 | B27: ='P&L'!X33 -> 989503 | C27: ='P&L'!X29 -> 45149 | D27: ='P&L'!X30 -> 906000 | E27: ='P&L'!X31 -> 36240 | F27: ='P&L'!X37 -> 54964 | G27: ='P&L'!X38 -> 934539 | H27: ='P&L'!X40 -> 27694.993 | I27: ='P&L'!X41 -> 906844.01 | J27: ='P&L'!X39 -> 0.94445292 | K27: ='P&L'!X42 -> 0.91646413
A28: M23 | B28: ='P&L'!Y33 -> 1245070 | C28: ='P&L'!Y29 -> 56810 | D28: ='P&L'!Y30 -> 1140000 | E28: ='P&L'!Y31 -> 45600 | F28: ='P&L'!Y37 -> 69160 | G28: ='P&L'!Y38 -> 1175910 | H28: ='P&L'!Y40 -> 27694.993 | I28: ='P&L'!Y41 -> 1148215 | J28: ='P&L'!Y39 -> 0.94445292 | K28: ='P&L'!Y42 -> 0.9222092
A29: M24 | B29: ='P&L'!Z33 -> 1566167 | C29: ='P&L'!Z29 -> 71461 | D29: ='P&L'!Z30 -> 1434000 | E29: ='P&L'!Z31 -> 57360 | F29: ='P&L'!Z37 -> 86996 | G29: ='P&L'!Z38 -> 1479171 | H29: ='P&L'!Z40 -> 27694.993 | I29: ='P&L'!Z41 -> 1451476 | J29: ='P&L'!Z39 -> 0.94445292 | K29: ='P&L'!Z42 -> 0.92676963
A31: Data validation: Dashboard linked to P&L with churn-adjusted carriers

Sheet Cash Flow Dashboard
A1: VELOCITYMATCH - CASH FLOW DASHBOARD
A2: Cash Position & Runway Analysis
A5: Month | B5: Beginning Cash | C5: Cash Inflows | D5: Cash Outflows | E5: Net Cash Flow | F5: Ending Cash | G5: Runway (Months)
A6: M1 | B6: ='Cash Flow'!C15 -> 187974 | C6: ='Cash Flow'!C18 -> 0 | D6: ='Cash Flow'!C22 -> 95349.5 | E6: ='Cash Flow'!C23 -> -95349.5 | F6: ='Cash Flow'!C24 -> 92624.5 | G6: ='Cash Flow'!C26 -> 4.8776692
A7: M2 | B7: ='Cash Flow'!D15 -> 92624.5 | C7: ='Cash Flow'!D18 -> 23989.4 | D7: ='Cash Flow'!D22 -> 20689.5 | E7: ='Cash Flow'!D23 -> 3299.9 | F7: ='Cash Flow'!D24 -> 95924.4 | G7: ='Cash Flow'!D26 -> 5.0514442
A8: M3 | B8: ='Cash Flow'!E15 -> 95924.4 | C8: ='Cash Flow'!E18 -> 29986.75 | D8: ='Cash Flow'!E22 -> 25833.667 | E8: ='Cash Flow'!E23 -> 4153.0833 | F8: ='Cash Flow'!E24 -> 100077.48 | G8: ='Cash Flow'!E26 -> 4.2060555
A9: M4 | B9: ='Cash Flow'!F15 -> 100077.48 | C9: ='Cash Flow'!F18 -> 35984.1 | D9: ='Cash Flow'!F22 -> 26341.667 | E9: ='Cash Flow'!F23 -> 9642.4333 | F9: ='Cash Flow'!F24 -> 109719.92 | G9: ='Cash Flow'!F26 -> 4.5174021
A10: M5 | B10: ='Cash Flow'!G15 -> 109719.92 | C10: ='Cash Flow'!G18 -> 43577.45 | D10: ='Cash Flow'!G22 -> 26705.667 | E10: ='Cash Flow'!G23 -> 16871.783 | F10: ='Cash Flow'!G24 -> 126591.7 | G10: ='Cash Flow'!G26 -> 4.814532
A11: M6 | B11: ='Cash Flow'!H15 -> 126591.7 | C11: ='Cash Flow'!H18 -> 49802.8 | D11: ='Cash Flow'!H22 -> 27069.667 | E11: ='Cash Flow'!H23 -> 22733.133 | F11: ='Cash Flow'!H24 -> 149324.83 | G11: ='Cash Flow'!H26 -> 5.5915037
A12: M7 | B12: ='Cash Flow'!I15 -> 149324.83 | C12: ='Cash Flow'!I18 -> 56028.15 | D12: ='Cash Flow'!I22 -> 28817.267 | E12: ='Cash Flow'!I23 -> 27210.883 | F12: ='Cash Flow'!I24 -> 176535.72 | G12: ='Cash Flow'!I26 -> 6.4122833
A13: M8 | B13: ='Cash Flow'!J15 -> 176535.72 | C13: ='Cash Flow'!J18 -> 62253.5 | D13: ='Cash Flow'!J22 -> 29181.267 | E13: ='Cash Flow'!J23 -> 33072.233 | F13: ='Cash Flow'!J24 -> 209607.95 | G13: ='Cash Flow'!J26 -> 7.3919967
A14: M9 | B14: ='Cash Flow'!K15 -> 209607.95 | C14: ='Cash Flow'!K18 -> 68478.85 | D14: ='Cash Flow'!K22 -> 29545.267 | E14: ='Cash Flow'!K23 -> 38933.583 | F14: ='Cash Flow'!K24 -> 248541.53 | G14: ='Cash Flow'!K26 -> 8.5171606
A15: M10 | B15: ='Cash Flow'!L15 -> 248541.53 | C15: ='Cash Flow'!L18 -> 74704.2 | D15: ='Cash Flow'!L22 -> 29909.267 | E15: ='Cash Flow'!L23 -> 44794.933 | F15: ='Cash Flow'!L24 -> 293336.47 | G15: ='Cash Flow'!L26 -> 9.9283743
A16: M11 | B16: ='Cash Flow'!M15 -> 293336.47 | C16: ='Cash Flow'!M18 -> 80929.55 | D16: ='Cash Flow'!M22 -> 30273.267 | E16: ='Cash Flow'!M23 -> 50656.283 | F16: ='Cash Flow'!M24 -> 343992.75 | G16: ='Cash Flow'!M26 -> 11.50121
A17: M12 | B17: ='Cash Flow'!N15 -> 343992.75 | C17: ='Cash Flow'!N18 -> 87154.9 | D17: ='Cash Flow'!N22 -> 30637.267 | E17: ='Cash Flow'!N23 -> 56517.633 | F17: ='Cash Flow'!N24 -> 400510.38 | G17: ='Cash Flow'!N26 -> 13.229837
A18: M13 | B18: ='Cash Flow'!O15 -> 400510.38 | C18: ='Cash Flow'!O18 -> 93380.25 | D18: ='Cash Flow'!O22 -> 34610.993 | E18: ='Cash Flow'!O23 -> 58769.257 | F18: ='Cash Flow'!O24 -> 459279.64 | G18: ='Cash Flow'!O26 -> 14.424381
A19: M14 | B19: ='Cash Flow'!P15 -> 459279.64 | C19: ='Cash Flow'!P18 -> 118281.65 | D19: ='Cash Flow'!P22 -> 36430.993 | E19: ='Cash Flow'!P23 -> 81850.657 | F19: ='Cash Flow'!P24 -> 541130.3 | G19: ='Cash Flow'!P26 -> 15.965803
A20: M15 | B20: ='Cash Flow'!Q15 -> 541130.3 | C20: ='Cash Flow'!Q18 -> 149408.4 | D20: ='Cash Flow'!Q22 -> 38614.993 | E20: ='Cash Flow'!Q23 -> 110793.41 | F20: ='Cash Flow'!Q24 -> 651923.7 | G20: ='Cash Flow'!Q26 -> 17.835354
A21: M16 | B21: ='Cash Flow'!R15 -> 651923.7 | C21: ='Cash Flow'!R18 -> 186760.5 | D21: ='Cash Flow'!R22 -> 41526.993 | E21: ='Cash Flow'!R23 -> 145233.51 | F21: ='Cash Flow'!R24 -> 797157.21 | G21: ='Cash Flow'!R26 -> 20.514802
A22: M17 | B22: ='Cash Flow'!S15 -> 797157.21 | C22: ='Cash Flow'!S18 -> 236563.3 | D22: ='Cash Flow'!S22 -> 44802.993 | E22: ='Cash Flow'!S23 -> 191760.31 | F22: ='Cash Flow'!S24 -> 988917.52 | G22: ='Cash Flow'!S26 -> 23.744472
A23: M18 | B23: ='Cash Flow'!T15 -> 988917.52 | C23: ='Cash Flow'!T18 -> 292591.45 | D23: ='Cash Flow'!T22 -> 49170.993 | E23: ='Cash Flow'!T23 -> 243420.46 | F23: ='Cash Flow'!T24 -> 1232338 | G23: ='Cash Flow'!T26 -> 27.284038
A24: M19 | B24: ='Cash Flow'!U15 -> 1232338 | C24: ='Cash Flow'!U18 -> 367295.65 | D24: ='Cash Flow'!U22 -> 54994.993 | E24: ='Cash Flow'!U23 -> 312300.66 | F24: ='Cash Flow'!U24 -> 1544638.6 | G24: ='Cash Flow'!U26 -> 31.106583
A25: M20 | B25: ='Cash Flow'!V15 -> 1544638.6 | C25: ='Cash Flow'!V18 -> 466901.25 | D25: ='Cash Flow'!V22 -> 62274.993 | E25: ='Cash Flow'!V23 -> 404626.26 | F25: ='Cash Flow'!V24 -> 1949264.9 | G25: ='Cash Flow'!V26 -> 35.134344
A26: M21 | B26: ='Cash Flow'!W15 -> 1949264.9 | C26: ='Cash Flow'!W18 -> 591408.25 | D26: ='Cash Flow'!W22 -> 71374.993 | E26: ='Cash Flow'!W23 -> 520033.26 | F26: ='Cash Flow'!W24 -> 2469298.1 | G26: ='Cash Flow'!W26 -> 39.268972
A27: M22 | B27: ='Cash Flow'!X15 -> 2469298.1 | C27: ='Cash Flow'!X18 -> 747042 | D27: ='Cash Flow'!X22 -> 82658.993 | E27: ='Cash Flow'!X23 -> 664383.01 | F27: ='Cash Flow'!X24 -> 3133681.1 | G27: ='Cash Flow'!X26 -> 43.46118
A28: M23 | B28: ='Cash Flow'!Y15 -> 3133681.1 | C28: ='Cash Flow'!Y18 -> 940027.85 | D28: ='Cash Flow'!Y22 -> 96854.993 | E28: ='Cash Flow'!Y23 -> 843172.86 | F28: ='Cash Flow'!Y24 -> 3976854 | G28: ='Cash Flow'!Y26 -> 47.553153
A29: M24 | B29: ='Cash Flow'!Z15 -> 3976854 | C29: ='Cash Flow'!Z18 -> 1182816.5 | D29: ='Cash Flow'!Z22 -> 114690.99 | E29: ='Cash Flow'!Z23 -> 1068125.5 | F29: ='Cash Flow'!Z24 -> 5044979.5 | G29: ='Cash Flow'!Z26 -> 51.443516
A31: Data validation: Dashboard linked to Cash Flow projections

Sheet Growth Metrics
A1: VELOCITYMATCH - GROWTH METRICS DASHBOARD
A2: Customer Acquisition & Revenue Performance
A5: Month | B5: Active Carriers | C5: New Carriers | D5: Total Revenue | E5: Revenue/Carrier | F5: Placements | G5: Placements/Carrier
A6: M1 | B6: ='Churn Model'!E29 -> 4 | C6: ='P&L'!C28 -> 4 | D6: ='P&L'!C33 -> 25252 | E6: =IFERROR(IF(B6=0,0,D6/B6), 0) -> 6313 | F6: =IFERROR('P&L'!C30/1200, 0) -> 20 | G6: =IFERROR(IF(B6=0,0,F6/B6), 0) -> 5
A7: M2 | B7: ='Churn Model'!E30 -> 5 | C7: ='P&L'!D28-'P&L'!C28 -> 1 | D7: ='P&L'!D33 -> 31565 | E7: =IFERROR(IF(B7=0,0,D7/B7), 0) -> 6313 | F7: =IFERROR('P&L'!D30/1200, 0) -> 25 | G7: =IFERROR(IF(B7=0,0,F7/B7), 0) -> 5
A8: M3 | B8: ='Churn Model'!E31 -> 6 | C8: ='P&L'!E28-'P&L'!D28 -> 1 | D8: ='P&L'!E33 -> 37878 | E8: =IFERROR(IF(B8=0,0,D8/B8), 0) -> 6313 | F8: =IFERROR('P&L'!E30/1200, 0) -> 30 | G8: =IFERROR(IF(B8=0,0,F8/B8), 0) -> 5
A9: M4 | B9: ='Churn Model'!E32 -> 7 | C9: ='P&L'!F28-'P&L'!E28 -> 1 | D9: ='P&L'!F33 -> 45871 | E9: =IFERROR(IF(B9=0,0,D9/B9), 0) -> 6553 | F9: =IFERROR('P&L'!F30/1200, 0) -> 35 | G9: =IFERROR(IF(B9=0,0,F9/B9), 0) -> 5
A10: M5 | B10: ='Churn Model'!E33 -> 8 | C10: ='P&L'!G28-'P&L'!F28 -> 1 | D10: ='P&L'!G33 -> 52424 | E10: =IFERROR(IF(B10=0,0,D10/B10), 0) -> 6553 | F10: =IFERROR('P&L'!G30/1200, 0) -> 40 | G10: =IFERROR(IF(B10=0,0,F10/B10), 0) -> 5
A11: M6 | B11: ='Churn Model'!E34 -> 9 | C11: ='P&L'!H28-'P&L'!G28 -> 1 | D11: ='P&L'!H33 -> 58977 | E11: =IFERROR(IF(B11=0,0,D11/B11), 0) -> 6553 | F11: =IFERROR('P&L'!H30/1200, 0) -> 45 | G11: =IFERROR(IF(B11=0,0,F11/B11), 0) -> 5
A12: M7 | B12: ='Churn Model'!E35 -> 10 | C12: ='P&L'!I28-'P&L'!H28 -> 1 | D12: ='P&L'!I33 -> 65530 | E12: =IFERROR(IF(B12=0,0,D12/B12), 0) -> 6553 | F12: =IFERROR('P&L'!I30/1200, 0) -> 50 | G12: =IFERROR(IF(B12=0,0,F12/B12), 0) -> 5
A13: M8 | B13: ='Churn Model'!E36 -> 11 | C13: ='P&L'!J28-'P&L'!I28 -> 1 | D13: ='P&L'!J33 -> 72083 | E13: =IFERROR(IF(B13=0,0,D13/B13), 0) -> 6553 | F13: =IFERROR('P&L'!J30/1200, 0) -> 55 | G13: =IFERROR(IF(B13=0,0,F13/B13), 0) -> 5
A14: M9 | B14: ='Churn Model'!E37 -> 12 | C14: ='P&L'!K28-'P&L'!J28 -> 1 | D14: ='P&L'!K33 -> 78636 | E14: =IFERROR(IF(B14=0,0,D14/B14), 0) -> 6553 | F14: =IFERROR('P&L'!K30/1200, 0) -> 60 | G14: =IFERROR(IF(B14=0,0,F14/B14), 0) -> 5
A15: M10 | B15: ='Churn Model'!E38 -> 13 | C15: ='P&L'!L28-'P&L'!K28 -> 1 | D15: ='P&L'!L33 -> 85189 | E15: =IFERROR(IF(B15=0,0,D15/B15), 0) -> 6553 | F15: =IFERROR('P&L'!L30/1200, 0) -> 65 | G15: =IFERROR(IF(B15=0,0,F15/B15), 0) -> 5
A16: M11 | B16: ='Churn Model'!E39 -> 14 | C16: ='P&L'!M28-'P&L'!L28 -> 1 | D16: ='P&L'!M33 -> 91742 | E16: =IFERROR(IF(B16=0,0,D16/B16), 0) -> 6553 | F16: =IFERROR('P&L'!M30/1200, 0) -> 70 | G16: =IFERROR(IF(B16=0,0,F16/B16), 0) -> 5
A17: M12 | B17: ='Churn Model'!E40 -> 15 | C17: ='P&L'!N28-'P&L'!M28 -> 1 | D17: ='P&L'!N33 -> 98295 | E17: =IFERROR(IF(B17=0,0,D17/B17), 0) -> 6553 | F17: =IFERROR('P&L'!N30/1200, 0) -> 75 | G17: =IFERROR(IF(B17=0,0,F17/B17), 0) -> 5
A18: M13 | B18: ='Churn Model'!E41 -> 19 | C18: ='P&L'!O28-'P&L'!N28 -> 4 | D18: ='P&L'!O33 -> 124507 | E18: =IFERROR(IF(B18=0,0,D18/B18), 0) -> 6553 | F18: =IFERROR('P&L'!O30/1200, 0) -> 95 | G18: =IFERROR(IF(B18=0,0,F18/B18), 0) -> 5
A19: M14 | B19: ='Churn Model'!E42 -> 24 | C19: ='P&L'!P28-'P&L'!O28 -> 5 | D19: ='P&L'!P33 -> 157272 | E19: =IFERROR(IF(B19=0,0,D19/B19), 0) -> 6553 | F19: =IFERROR('P&L'!P30/1200, 0) -> 120 | G19: =IFERROR(IF(B19=0,0,F19/B19), 0) -> 5
A20: M15 | B20: ='Churn Model'!E43 -> 30 | C20: ='P&L'!Q28-'P&L'!P28 -> 6 | D20: ='P&L'!Q33 -> 196590 | E20: =IFERROR(IF(B20=0,0,D20/B20), 0) -> 6553 | F20: =IFERROR('P&L'!Q30/1200, 0) -> 150 | G20: =IFERROR(IF(B20=0,0,F20/B20), 0) -> 5
A21: M16 | B21: ='Churn Model'!E44 -> 38 | C21: ='P&L'!R28-'P&L'!Q28 -> 8 | D21: ='P&L'!R33 -> 249014 | E21: =IFERROR(IF(B21=0,0,D21/B21), 0) -> 6553 | F21: =IFERROR('P&L'!R30/1200, 0) -> 190 | G21: =IFERROR(IF(B21=0,0,F21/B21), 0) -> 5
A22: M17 | B22: ='Churn Model'!E45 -> 47 | C22: ='P&L'!S28-'P&L'!R28 -> 9 | D22: ='P&L'!S33 -> 307991 | E22: =IFERROR(IF(B22=0,0,D22/B22), 0) -> 6553 | F22: =IFERROR('P&L'!S30/1200, 0) -> 235 | G22: =IFERROR(IF(B22=0,0,F22/B22), 0) -> 5
A23: M18 | B23: ='Churn Model'!E46 -> 59 | C23: ='P&L'!T28-'P&L'!S28 -> 12 | D23: ='P&L'!T33 -> 386627 | E23: =IFERROR(IF(B23=0,0,D23/B23), 0) -> 6553 | F23: =IFERROR('P&L'!T30/1200, 0) -> 295 | G23: =IFERROR(IF(B23=0,0,F23/B23), 0) -> 5
A24: M19 | B24: ='Churn Model'!E47 -> 75 | C24: ='P&L'!U28-'P&L'!T28 -> 16 | D24: ='P&L'!U33 -> 491475 | E24: =IFERROR(IF(B24=0,0,D24/B24), 0) -> 6553 | F24: =IFERROR('P&L'!U30/1200, 0) -> 375 | G24: =IFERROR(IF(B24=0,0,F24/B24), 0) -> 5
A25: M20 | B25: ='Churn Model'!E48 -> 95 | C25: ='P&L'!V28-'P&L'!U28 -> 20 | D25: ='P&L'!V33 -> 622535 | E25: =IFERROR(IF(B25=0,0,D25/B25), 0) -> 6553 | F25: =IFERROR('P&L'!V30/1200, 0) -> 475 | G25: =IFERROR(IF(B25=0,0,F25/B25), 0) -> 5
A26: M21 | B26: ='Churn Model'!E49 -> 120 | C26: ='P&L'!W28-'P&L'!V28 -> 25 | D26: ='P&L'!W33 -> 786360 | E26: =IFERROR(IF(B26=0,0,D26/B26), 0) -> 6553 | F26: =IFERROR('P&L'!W30/1200, 0) -> 600 | G26: =IFERROR(IF(B26=0,0,F26/B26), 0) -> 5
A27: M22 | B27: ='Churn Model'!E50 -> 151 | C27: ='P&L'!X28-'P&L'!W28 -> 31 | D27: ='P&L'!X33 -> 989503 | E27: =IFERROR(IF(B27=0,0,D27/B27), 0) -> 6553 | F27: =IFERROR('P&L'!X30/1200, 0) -> 755 | G27: =IFERROR(IF(B27=0,0,F27/B27), 0) -> 5
A28: M23 | B28: ='Churn Model'!E51 -> 190 | C28: ='P&L'!Y28-'P&L'!X28 -> 39 | D28: ='P&L'!Y33 -> 1245070 | E28: =IFERROR(IF(B28=0,0,D28/B28), 0) -> 6553 | F28: =IFERROR('P&L'!Y30/1200, 0) -> 950 | G28: =IFERROR(IF(B28=0,0,F28/B28), 0) -> 5
A29: M24 | B29: ='Churn Model'!E52 -> 239 | C29: ='P&L'!Z28-'P&L'!Y28 -> 49 | D29: ='P&L'!Z33 -> 1566167 | E29: =IFERROR(IF(B29=0,0,D29/B29), 0) -> 6553 | F29: =IFERROR('P&L'!Z30/1200, 0) -> 1195 | G29: =IFERROR(IF(B29=0,0,F29/B29), 0) -> 5
A31: Data validation: Carrier counts now reflect churn impact

Sheet Scenario Analysis
A1: VELOCITYMATCH - SCENARIO ANALYSIS
A2: Best Case / Base Case / Worst Case Projections | Yellow cells are adjustable inputs
A4: SCENARIO PARAMETERS
A6: Parameter | B6: Worst Case | C6: Base Case | D6: Best Case | E6: Pessimistic | F6: Recession | G6: Unit | H6: Notes
A7: Starting Carriers | B7: =Assumptions!B144 -> 2 | C7: =Assumptions!B145 -> 4 | D7: =Assumptions!B146 -> 6 | E7: =Assumptions!B147 -> 3 | F7: =Assumptions!B148 -> 1 | G7: carriers | H7: Initial beta customers
A8: Monthly Growth Y1 | B8: =Assumptions!B149 -> 0.1 | C8: =Assumptions!B150 -> 0.15 | D8: =Assumptions!B151 -> 0.2 | E8: =Assumptions!B152 -> 0.08 | F8: =Assumptions!B153 -> 0.03 | G8: % | H8: Month-over-month growth
A9: Monthly Growth Y2 | B9: =Assumptions!B154 -> 0.15 | C9: =Assumptions!B155 -> 0.3 | D9: =Assumptions!B156 -> 0.4 | E9: =Assumptions!B157 -> 0.12 | F9: =Assumptions!B158 -> 0.05 | G9: % | H9: Scaling phase growth
A10: Monthly Churn Y1 | B10: =Assumptions!B159 -> 0.08 | C10: =Assumptions!B158 -> 0.05 | D10: =Assumptions!B153 -> 0.03 | E10: =Assumptions!B160 -> 0.1 | F10: =Assumptions!B161 -> 0.15 | G10: % | H10: Customer attrition
A11: Monthly Churn Y2 | B11: =Assumptions!B162 -> 0.06 | C11: =Assumptions!B163 -> 0.04 | D11: =Assumptions!B164 -> 0.02 | E11: =Assumptions!B165 -> 0.08 | F11: =Assumptions!B166 -> 0.12 | G11: % | H11: Improved retention
A12: Placements/Carrier | B12: 3 | C12: 5 | D12: 7 | E12: 4 | F12: 2 | G12: placements | H12: Average monthly placements
A13: Add-on Attach Rate | B13: =Assumptions!B167 -> 0.4 | C13: 0.6 | D13: 0.75 | E13: =Assumptions!B168 -> 0.3 | F13: =Assumptions!B169 -> 0.2 | G13: % | H13: Cross-sell success
A14: Placement Fee | B14: 1000 | C14: =Assumptions!B170 -> 1200 | D14: =Assumptions!B171 -> 1400 | E14: 1000 | F14: 800 | G14: $ | H14: Per-hire pricing
A15: Matching Engine Fee | B15: 249 | C15: =Assumptions!B172 -> 299 | D15: 349 | E15: 249 | F15: 199 | G15: $/month | H15: Core subscription
A18: SCENARIO OUTPUTS - 24 MONTH PROJECTIONS
A20: Metric | B20: Worst Case | C20: Base Case | D20: Best Case | G20: Notes
A21: Y1 Ending Carriers | B21: =ROUND(B7*(1+B8)^12*(1-B10)^12,0) -> 2 | C21: =ROUND(C7*(1+C8)^12*(1-C10)^12,0) -> 12 | D21: =ROUND(D7*(1+D8)^12*(1-D10)^12,0) -> 37 | G21: Net of growth and churn
A22: Y2 Ending Carriers | B22: =ROUND(B21*(1+B9)^12*(1-B11)^12,0) -> 5 | C22: =ROUND(C21*(1+C9)^12*(1-C11)^12,0) -> 171 | D22: =ROUND(D21*(1+D9)^12*(1-D11)^12,0) -> 1646 | G22: Second year projection
A23: Y1 Total Revenue | B23: =B21*12*(B14+B12*B15+B13*400) -> 45768 | C23: =C21*12*(C14+C12*C15+C13*400) -> 422640 | D23: =D21*12*(D14+D12*D15+D13*400) -> 1839492 | G23: Subscription + Placements + Add-ons
A24: Y2 Total Revenue | B24: =B22*12*(B14+B12*B15+B13*400) -> 114420 | C24: =C22*12*(C14+C12*C15+C13*400) -> 6022620 | D24: =D22*12*(D14+D12*D15+D13*400) -> 81832536 | G24: Second year revenue
A25: 24-Month Total Revenue | B25: =B23+B24 -> 160188 | C25: =C23+C24 -> 6445260 | D25: =D23+D24 -> 83672028 | G25: Combined two-year revenue
A26: Y1 Monthly Burn Rate | B26: =Assumptions!B173 -> 15000 | C26: =Assumptions!B174 -> 12000 | D26: =Assumptions!B175 -> 10000 | G26: Operating expenses (estimate)
A27: Runway Required (months) | B27: =IFERROR(IF(B26>0,ROUND('Startup Costs-Led BuildWA'!$B$90/B26,0),0), 0) -> 13 | C27: =IFERROR(IF(C26>0,ROUND('Startup Costs-Led BuildWA'!$B$90/C26,0),0), 0) -> 16 | D27: =IFERROR(IF(D26>0,ROUND('Startup Costs-Led BuildWA'!$B$90/D26,0),0), 0) -> 19 | G27: Capital needed pre-profitability
A30: BREAKEVEN ANALYSIS
A32: Scenario | B32: Est. Breakeven Month | C32: Monthly Revenue at BE | D32: Confidence Level
A33: Worst Case | B33: 24 | C33: =B26 -> 15000 | D33: Low (20%)
A34: Base Case | B34: 18 | C34: =C26 -> 12000 | D34: Medium (60%)
A35: Best Case | B35: 12 | C35: =D26 -> 10000 | D35: Aspirational (20%)

Sheet Platform Roadmap
A1: VELOCITYMATCH - PLATFORM ROADMAP
A2: 11-Layer Technology Stack Evolution (8 Core + 3 Expansion)
A4: Layer | B4: Name | C4: Description | D4: Key Features | E4: Revenue Streams | F4: Timeline | G4: Investment
A5: 1 | B5: AI Matching Engine | C5: Core driver-carrier matching algorithm | D5: ML matching, skill analysis, preference learning | E5: Per-Hire Fees, Matching Subscriptions, Usage-Based Credits | F5: M1-M6 (MVP) | G5: $187K
A6: 2 | B6: Data & Intelligence | C6: Monetizable insights and data services | D6: Market analytics, compensation benchmarking, turnover prediction | E6: Intelligence Subscriptions, API Access, Data Licenses | F6: M7-M12 | G6: $150K
A7: 3 | B7: Brokerage Automation | C7: Automates freight brokerage tasks | D7: Automated driver-carrier matching for freight brokers | E7: Per-Load Fees, Booking Fees, Automation Add-Ons | F7: M10-M15 | G7: $175K
A8: 4 | B8: Operations Automation | C8: Automates daily fleet and dispatch operations | D8: DQ file compliance, onboarding workflows, document mgmt | E8: Fleet SaaS Subscriptions, Workflow Automation, Predictive Maintenance | F8: M12-M18 | G8: $200K
A9: 5 | B9: Application Suite | C9: Interfaces for shippers, carriers, drivers, and recruiters | D9: Mobile apps, web dashboards, recruiter tools | E9: SaaS Subscriptions, LMS Seats, Training Modules | F9: M15-M21 | G9: $225K
A10: 6 | B10: Integrations | C10: Connections to TMS, ELDs, factoring, robotics, load boards | D10: API connections, data sync, webhook events | E10: Integration Fees, API Usage, Enterprise Implementation | F10: M18-M24 | G10: $250K
A11: 7 | B11: Analytics & Telematics | C11: Insights, behavior monitoring, performance dashboards | D11: ELD data ingestion, safety scores, driver behavior analytics | E11: Analytics Subscriptions, KPI Dashboards, Predictive Maintenance Intelligence | F11: M21-M30 | G11: $400K
A12: 8 | B12: Enterprise Control Layer | C12: Admin tools for billing, permissions, workflows | D12: Multi-location mgmt, SSO, admin controls, white-label | E12: Enterprise SaaS, Admin Add-Ons, Multi-Tenant Licensing | F12: M24-M36 | G12: $500K
A13: 9 | B13: Marketplace Platform | C13: Two-sided marketplace for drivers and carriers | D13: Carrier lead swap, Driver profiles, carrier listings, real-time availability matching | E13: Platform Fees, Premium Listings, Featured Placements | F13: M30-M42 | G13: $600K
A14: =Assumptions!B176 -> 10 | B14: Financial Services | C14: Embedded fintech for trucking ecosystem | D14: Factoring partnerships, fuel cards, equipment financing, insurance | E14: Referral Fees, Revenue Share, Embedded Finance Margins | F14: M36-M48 | G14: $750K
A15: 11 | B15: Network Effects Platform | C15: Multi-carrier coordination and capacity sharing | D15: Load sharing, driver pools, capacity networks, surge pricing | E15: Transaction Fees, Network Subscriptions, Capacity Premiums | F15: M42-M54 | G15: $900K
A18: INVESTMENT SUMMARY BY PHASE
A20: Phase | B20: Layers | C20: Total Investment | D20: Cumulative ARR Target | E20: Timeline
A21: Seed (Current) | B21: 1 | C21: =Assumptions!B177 -> 187974 | D21: $500K | E21: M1-M6
A22: Series A | B22: 2-4 | C22: =Assumptions!B178 -> 525000 | D22: $2M | E22: M7-M18
A23: Series B | B23: 5-8 | C23: =Assumptions!B179 -> 1375000 | D23: $10M | E23: M15-M36
A24: Series C | B24: 9-10 | C24: =Assumptions!B180 -> 1350000 | D24: $30M | E24: M30-M48
A25: Growth | B25: =Assumptions!B181 -> 11 | C25: =Assumptions!B182 -> 900000 | D25: $75M+ | E25: M42-M54
A28: LEGEND
A29: Green = Current Focus (Layer 1)
A30: Blue = Official Roadmap (Layers 2-8)
A31: Orange = Expansion Layers (Layers 9-11)
A33: TOTAL PLATFORM INVESTMENT: | B33: =Assumptions!B183 -> 4337974

Sheet Assumptions
A1: VELOCITYMATCH LAYER 1 - FINANCIAL MODEL ASSUMPTIONS
A2: AI Matching Engine Revenue Model
A3: Generated: December 17, 2025
A5: Category | B5: Assumption | C5: Value | D5: Unit | E5: Notes
A6: REVENUE MODEL
A7: Placement Pricing | B7: Per-Hire Placement Fee | C7: 1200 | D7: $ | E7: Core revenue per successful driver placement
A8: Placement Pricing | B8: Setup Fee (One-Time) | C8: 100 | D8: $ | E8: Initial carrier onboarding fee (included in placement)
A9: Placement Pricing | B9: Net Revenue per Placement | C9: 1200 | D9: $ | E9: Total revenue per completed placement
A10: Placement Pricing | B10: Matching Engine Subscription | C10: 299 | D10: $/month | E10: Core subscription fee for AI matching platform
A12: MARKET & GROWTH
A13: Market Size | B13: Total US CDL Drivers | C13: 3500000 | D13: drivers | E13: Addressable market (ATA 2024 data)
A14: Market Size | B14: Annual Driver Turnover | C14: 94 | D14: % | E14: Industry turnover rate (ATRI 2024)
A15: Market Size | B15: Annual Hiring Need | C15: 3290000 | D15: hires/year | E15: Market opportunity = 3.5M × 94%
A16: Growth Rates | B16: Year 1 Monthly Placement Growth | C16: 15 | D16: % | E16: Initial traction phase growth rate
A17: Growth Rates | B17: Year 2 Monthly Placement Growth | C17: 30 | D17: % | E17: Scaling phase with market validation (aligned with P&L)
A18: Growth Rates | B18: Year 3+ Monthly Placement Growth | C18: 25 | D18: % | E18: Full market penetration phase
A20: CUSTOMER ACQUISITION
A21: Driver Acquisition | B21: Driver CAC (Paid Ads) | C21: 16.28 | D21: $/lead | E21: Based on Last Mile campaign data (Dec 2025)
A22: Driver Acquisition | B22: Driver Conversion Rate | C22: 35 | D22: % | E22: Lead to completed onboarding
A23: Driver Acquisition | B23: Effective Driver CAC | C23: 46.51 | D23: $/driver | E23: CAC ÷ conversion rate
A24: Driver Acquisition | B24: Driver Lead Sources | C24: Meta Platform Ads, X, Google PPC, LinkedIn, Organic | E24: Multi-channel acquisition strategy
A26: Carrier Acquisition | B26: Carrier CAC (TMS SaaS Benchmark) | C26: 450 | D26: $/carrier | E26: Industry benchmark for TMS software
A27: Carrier Acquisition | B27: Carrier Onboarding Time | C27: 14 | D27: days | E27: Average time to first placement
A28: Carrier Acquisition | B28: Carriers per Sales Rep (Annual) | C28: 48 | D28: carriers | E28: Enterprise sales productivity
A29: Carrier Acquisition | B29: Average Fleet Size (Carriers) | C29: 125 | D29: trucks | E29: Target carrier profile
A31: UNIT ECONOMICS
A32: Placement Metrics | B32: Average Time to Placement | C32: 7 | D32: days | E32: From driver application to hire
A33: Placement Metrics | B33: Match Success Rate | C33: 85 | D33: % | E33: Successful placements vs attempts
A34: Placement Metrics | B34: Driver Retention (90-Day) | C34: 78 | D34: % | E34: Industry benchmark for quality placements
A35: Placement Metrics | B35: Replacement Guarantee Period | C35: 30 | D35: days | E35: Free replacement window
A37: Contribution Margin | B37: Revenue per Placement | C37: 1200 | D37: $ | E37: Gross revenue
A38: Contribution Margin | B38: Variable Costs per Placement | C38: 65 | D38: $ | E38: Driver CAC + processing + support
A39: Contribution Margin | B39: Contribution Margin per Unit | C39: 1135 | D39: $ | E39: Revenue - variable costs
A40: Contribution Margin | B40: Contribution Margin % | C40: 94.6 | D40: % | E40: (Revenue - COGS) ÷ Revenue
A42: OPERATING EXPENSES
A43: Technology Infrastructure | B43: Google Cloud Platform (Monthly) | C43: 1200 | D43: $/month | E43: Compute, storage, ML services, redundancy
A44: Technology Infrastructure | B44: Third-Party Services (Monthly) | C44: 250 | D44: $/month | E44: Twilio, SendGrid, authentication, monitoring
A45: Technology Infrastructure | B45: Development Tools (Monthly) | C45: 400 | D45: $/month | E45: GitHub, dev infrastructure, web dev
A47: Personnel (Founder Phase) | B47: Founder Salary (Minimal) | C47: 3500 | D47: $/month | E47: Bare minimum living expenses
A48: Personnel (Founder Phase) | B48: Contract Developers (as needed) | C48: 85 | D48: $/hour | E48: Specialized development work
A49: Personnel (Founder Phase) | B49: Healthcare (Individual) | C49: 400 | D49: $/month | E49: High-deductible plan
A51: Sales & Marketing | B51: Driver Marketing Budget | C51: 3000 | D51: $/month | E51: Facebook, LinkedIn, job boards (scales with growth)
A52: Sales & Marketing | B52: Carrier Sales & Marketing | C52: 5000 | D52: $/month | E52: Outbound sales, demos, collateral
A53: Sales & Marketing | B53: Content & Brand | C53: 500 | D53: $/month | E53: Thought leadership, social media
A55: Legal & Compliance | B55: Freight Broker Insurance | C55: 650 | D55: $/month | E55: General liability, cargo, E&O
A56: Legal & Compliance | B56: Surety Bond (Annual) | C56: 1200 | D56: $/year | E56: $75K bond required by FMCSA
A57: Legal & Compliance | B57: Legal & Compliance (Monthly) | C57: 500 | D57: $/month | E57: Templates, compliance, contractor attorney
... A62: General & Administrative | B62: Business Phone | C62: 25 | D62: $/month | E62: VoIP professional line
A64: FINANCIAL PROJECTIONS
A65: Timeline | B65: MVP Launch Month | C65: 4 | D65: month | E65: First paid placement | G65: CHART DATA - MONTHLY OPERATING EXPENSES
A66: Timeline | B66: Break-Even Target | C66: 18 | D66: month | E66: Monthly profitability milestone | G66: Category | H66: Amount
A67: Timeline | B67: Product-Market Fit Signal | C67: 100 | D67: placements/month | E67: Validation of market demand | G67: Technology | H67: 1850
A68: Timeline | B68: Scale-Ready Signal | C68: 500 | D68: placements/month | E68: Ready for external funding | G68: Personnel | H68: 3900
G69: Marketing | H69: 8500
A70: Capital Requirements | B70: Startup Capital (6 Months) | C70: 187974 | D70: $ | E70: From FounderLed MVP analysis | G70: Legal & Compliance | H70: 1150
A71: Capital Requirements | B71: Runway Extension Reserve | C71: 50000 | D71: $ | E71: Additional 3-month buffer | G71: G&A | H71: 249
A72: Capital Requirements | B72: Total Seed Capital Target | C72: 237974 | D72: $ | E72: Full capitalization for launch
A73: Capital Requirements | B73: Monthly Burn Rate (Initial) | C73: 15204 | D73: $/month | E73: Average monthly expenses pre-revenue
A75: KEY METRICS | G75: CHART DATA - MARKETING BUDGET
A76: North Star Metrics | B76: Successful Placements per Month | C76: Variable | D76: placements | E76: Primary growth indicator | G76: Channel | H76: Amount
A77: North Star Metrics | B77: Monthly Recurring Revenue (MRR) | C77: Variable | D77: $ | E77: Predictable revenue stream from subscriptions | G77: Carrier Sales/Outreach | H77: 5000
A78: North Star Metrics | B78: LTV:CAC Ratio Target | C78: 3 | D78: ratio | E78: Customer lifetime value to acquisition cost | G78: Driver Marketing | H78: 3000
A79: North Star Metrics | B79: Gross Margin Target | C79: 95 | D79: % | E79: High-margin AI-powered business model | G79: Content & Brand | H79: 500
A81: Efficiency Metrics | B81: Revenue per Employee (Target) | C81: 250000 | D81: $/year | E81: Lean, tech-enabled operations
A82: Efficiency Metrics | B82: Magic Number (Target) | C82: 1.5 | D82: ratio | E82: Sales efficiency: Net new ARR ÷ S&M spend
A83: Efficiency Metrics | B83: Payback Period (Target) | C83: 6 | D83: months | E83: CAC payback period | G83: CHART DATA - REVENUE STREAMS (per carrier/month)
G84: Stream | H84: Amount
A85: RISKS & SENSITIVITIES | G85: Placement Services | H85: 6000
A86: Key Risks | B86: Driver Supply Risk | C86: Medium | E86: Competition for driver attention | G86: Matching Engine Sub | H86: 299
A87: Key Risks | B87: Carrier Adoption Risk | C87: Medium | E87: Sales cycle may extend in downturn | G87: Add-on Products | H87: 240
A88: Key Risks | B88: Technology Execution Risk | C88: Low | E88: Founder has technical capability | G88: Overage Revenue | H88: 14
A89: Key Risks | B89: Market Timing Risk | C89: Low | E89: Structural driver shortage remains
A91: Sensitivity Factors | B91: Placement Fee Variance | C91: ±20% | E91: Market pricing pressure range
A92: Sensitivity Factors | B92: CAC Variance | C92: ±30% | E92: Marketing efficiency range
A93: Sensitivity Factors | B93: Growth Rate Variance | C93: ±10% | E93: Market adoption uncertainty
A94: Sensitivity Factors | B94: Churn Rate Impact | C94: 5-15% | E94: Customer retention variability
A97: METHODOLOGY NOTES
A98: • Driver CAC based on actual Last Mile Advertising campaign data (Dec 7-17, 2025): $16.28 per lead
A99: • Carrier CAC uses TMS SaaS industry benchmark: $450 per carrier
A100: • Placement fee of $1,200 includes $100 setup fee (per user specifications)
A101: • Contribution margin calculated as: Revenue ($1,200) - Variable costs ($65) = $1,135 (94.6%)
A102: • Financial model assumes founder-led MVP build using Google Cloud Platform
A103: • Break-even analysis targets 18-month timeline to monthly profitability
A104: • All figures subject to market validation and actual performance data
A107: TAM/SAM/SOM ANALYSIS
A109: Market Level | B109: Description | C109: Value | D109: Calculation | E109: Notes
A110: TAM (Total Addressable Market) | B110: All US CDL driver hiring | C110: $3.95B | D110: 3.29M hires/year x $1,200 avg placement fee | E110: Entire US trucking recruitment market
A111: SAM (Serviceable Addressable Market) | B111: Tech-forward carriers (>50 trucks) | C111: $1.58B | D111: TAM x 40% (carriers likely to adopt SaaS) | E111: Carriers using technology for recruitment
A112: SOM (Serviceable Obtainable Market) | B112: Realistic Y3 capture | C112: $15.8M | D112: SAM x 1% market share | E112: Conservative 3-year target
A113: Y1 Target | B113: MVP validation | C113: $1.2M | D113: 1,000 placements x $1,200 | E113: Initial traction milestone
A114: Y2 Target | B114: Growth phase | C114: $6.5M | D114: ~5,400 placements + subscriptions | E114: Post product-market fit
A117: MARKET PENETRATION ANALYSIS
A119: Year | B119: Placements | C119: Market Share | D119: Revenue | E119: Notes
A120: Year 1 | B120: 1,000 | C120: 0.03% | D120: $1.2M | E120: Validation phase
A121: Year 2 | B121: 5,400 | C121: 0.16% | D121: $6.5M | E121: Growth acceleration
A122: Year 3 | B122: 15,000 | C122: 0.46% | D122: $18M | E122: Market establishment
A123: Year 5 | B123: 50,000 | C123: 1.52% | D123: $60M | E123: Major player status
A127: COMPETITIVE ANALYSIS
A129: Competitor | B129: Model | C129: Pricing | D129: Strengths | E129: Weaknesses | F129: Our Differentiation
A130: Tenstreet | B130: Job board + ATS | C130: $200-500/mo + per-app fees | D130: Market leader, established brand, full ATS | E130: No AI matching, legacy tech, expensive | F130: AI-first matching, lower cost, modern UX
...

Sheet Churn Model
A1: VELOCITYMATCH - CARRIER CHURN & RETENTION MODEL
A2: Customer Lifecycle Analysis | Yellow cells are inputs
A3: Generated: December 23, 2025
A5: CHURN ASSUMPTIONS
A6: Input | B6: Value | C6: Unit | D6: Notes | E6: Industry Benchmark
A7: Monthly Churn Rate (Y1) | B7: ='Scenario Analysis'!C10 -> 0.05 | C7: % | D7: Expected monthly carrier churn | E7: 5-7% for SaaS
A8: Monthly Churn Rate (Y2) | B8: ='Scenario Analysis'!C11 -> 0.04 | C8: % | D8: Improved with product maturity | E8: 3-5% for established
A9: Monthly Churn Rate (Y3+) | B9: =Assumptions!B153 -> 0.03 | C9: % | D9: Stable mature product | E9: 2-4% best-in-class
A10: Reactivation Rate | B10: =Assumptions!B184 -> 0.1 | C10: % | D10: Churned carriers who return | E10: 5-15% industry avg
A13: RETENTION & LIFETIME VALUE METRICS
A14: Metric | B14: Value | C14: Formula | D14: Notes
A15: Monthly Retention Rate (Y1) | B15: =1-B7 -> 0.95 | C15: =1 - Churn Rate -> #NAME? | D15: 95% retention monthly
A16: Annual Retention Rate (Y1) | B16: =B15^12 -> 0.54036009 | C16: =Monthly^12 -> #NAME? | D16: Compounded annual retention
A17: Customer Lifetime (months) | B17: =IFERROR(1/B7, "N/A") -> 20 | C17: =IFERROR(1 / Churn Rate, 0) -> 0 | D17: Average months before churn
A18: Revenue per Carrier/Month | B18: =Assumptions!B185 -> 6553 | C18: From P&L model | D18: Matching + Placements + Add-ons
A19: Customer Lifetime Value (LTV) | B19: =B17*B18 -> 131060 | C19: =Lifetime x Revenue -> #NAME? | D19: Total revenue per carrier
A20: Carrier Acquisition Cost (CAC) | B20: 450 | C20: From Assumptions | D20: TMS SaaS benchmark
A21: LTV:CAC Ratio | B21: =IFERROR(B19/B20, 0) -> 291.24444 | C21: =IFERROR(LTV / CAC, 0) -> 0 | D21: Target: >3:1 for healthy SaaS
A22: CAC Payback (months) | B22: =IFERROR(B20/B18, 0) -> 0.068670838 | C22: =IFERROR(CAC / Monthly Revenue, 0) -> 0 | D22: Target: <12 months
A25: CARRIER COHORT ANALYSIS - WITH CHURN
A26: Shows how churn impacts carrier count vs. P&L gross projections
A28: Month | B28: New Carriers | C28: Churned | D28: Retained | E28: Net Active | F28: Gross (No Churn) | G28: Churn Impact
A29: M1 | B29: 4 | C29: 0 | D29: 0 | E29: =B29 -> 4 | F29: 4 | G29: =F29-E29 -> 0
A30: M2 | B30: =MAX(1,ROUND(E29*0.15,0)) -> 1 | C30: =ROUND(E29*$B$7,0) -> 0 | D30: =E29-C30 -> 4 | E30: =B30+D30 -> 5 | F30: =ROUND(F29*1.15,0) -> 5 | G30: =F30-E30 -> 0
A31: M3 | B31: =MAX(1,ROUND(E30*0.15,0)) -> 1 | C31: =ROUND(E30*$B$7,0) -> 0 | D31: =E30-C31 -> 5 | E31: =B31+D31 -> 6 | F31: =ROUND(F30*1.15,0) -> 6 | G31: =F31-E31 -> 0
A32: M4 | B32: =MAX(1,ROUND(E31*0.15,0)) -> 1 | C32: =ROUND(E31*$B$7,0) -> 0 | D32: =E31-C32 -> 6 | E32: =B32+D32 -> 7 | F32: =ROUND(F31*1.15,0) -> 7 | G32: =F32-E32 -> 0
A33: M5 | B33: =MAX(1,ROUND(E32*0.15,0)) -> 1 | C33: =ROUND(E32*$B$7,0) -> 0 | D33: =E32-C33 -> 7 | E33: =B33+D33 -> 8 | F33: =ROUND(F32*1.15,0) -> 8 | G33: =F33-E33 -> 0
A34: M6 | B34: =MAX(1,ROUND(E33*0.15,0)) -> 1 | C34: =ROUND(E33*$B$7,0) -> 0 | D34: =E33-C34 -> 8 | E34: =B34+D34 -> 9 | F34: =ROUND(F33*1.15,0) -> 9 | G34: =F34-E34 -> 0
A35: M7 | B35: =MAX(1,ROUND(E34*0.15,0)) -> 1 | C35: =ROUND(E34*$B$7,0) -> 0 | D35: =E34-C35 -> 9 | E35: =B35+D35 -> 10 | F35: =ROUND(F34*1.15,0) -> 10 | G35: =F35-E35 -> 0
A36: M8 | B36: =MAX(1,ROUND(E35*0.15,0)) -> 2 | C36: =ROUND(E35*$B$7,0) -> 1 | D36: =E35-C36 -> 9 | E36: =B36+D36 -> 11 | F36: =ROUND(F35*1.15,0) -> 12 | G36: =F36-E36 -> 1
A37: M9 | B37: =MAX(1,ROUND(E36*0.15,0)) -> 2 | C37: =ROUND(E36*$B$7,0) -> 1 | D37: =E36-C37 -> 10 | E37: =B37+D37 -> 12 | F37: =ROUND(F36*1.15,0) -> 14 | G37: =F37-E37 -> 2
A38: M10 | B38: =MAX(1,ROUND(E37*0.15,0)) -> 2 | C38: =ROUND(E37*$B$7,0) -> 1 | D38: =E37-C38 -> 11 | E38: =B38+D38 -> 13 | F38: =ROUND(F37*1.15,0) -> 16 | G38: =F38-E38 -> 3
A39: M11 | B39: =MAX(1,ROUND(E38*0.15,0)) -> 2 | C39: =ROUND(E38*$B$7,0) -> 1 | D39: =E38-C39 -> 12 | E39: =B39+D39 -> 14 | F39: =ROUND(F38*1.15,0) -> 18 | G39: =F39-E39 -> 4
A40: M12 | B40: =MAX(1,ROUND(E39*0.15,0)) -> 2 | C40: =ROUND(E39*$B$7,0) -> 1 | D40: =E39-C40 -> 13 | E40: =B40+D40 -> 15 | F40: =ROUND(F39*1.15,0) -> 21 | G40: =F40-E40 -> 6
A41: M13 | B41: =MAX(1,ROUND(E40*0.3,0)) -> 5 | C41: =ROUND(E40*$B$8,0) -> 1 | D41: =E40-C41 -> 14 | E41: =B41+D41 -> 19 | F41: =ROUND(F40*1.3,0) -> 27 | G41: =F41-E41 -> 8
A42: M14 | B42: =MAX(1,ROUND(E41*0.3,0)) -> 6 | C42: =ROUND(E41*$B$8,0) -> 1 | D42: =E41-C42 -> 18 | E42: =B42+D42 -> 24 | F42: =ROUND(F41*1.3,0) -> 35 | G42: =F42-E42 -> 11
A43: M15 | B43: =MAX(1,ROUND(E42*0.3,0)) -> 7 | C43: =ROUND(E42*$B$8,0) -> 1 | D43: =E42-C43 -> 23 | E43: =B43+D43 -> 30 | F43: =ROUND(F42*1.3,0) -> 46 | G43: =F43-E43 -> 16
A44: M16 | B44: =MAX(1,ROUND(E43*0.3,0)) -> 9 | C44: =ROUND(E43*$B$8,0) -> 1 | D44: =E43-C44 -> 29 | E44: =B44+D44 -> 38 | F44: =ROUND(F43*1.3,0) -> 60 | G44: =F44-E44 -> 22
A45: M17 | B45: =MAX(1,ROUND(E44*0.3,0)) -> 11 | C45: =ROUND(E44*$B$8,0) -> 2 | D45: =E44-C45 -> 36 | E45: =B45+D45 -> 47 | F45: =ROUND(F44*1.3,0) -> 78 | G45: =F45-E45 -> 31
A46: M18 | B46: =MAX(1,ROUND(E45*0.3,0)) -> 14 | C46: =ROUND(E45*$B$8,0) -> 2 | D46: =E45-C46 -> 45 | E46: =B46+D46 -> 59 | F46: =ROUND(F45*1.3,0) -> 101 | G46: =F46-E46 -> 42
A47: M19 | B47: =MAX(1,ROUND(E46*0.3,0)) -> 18 | C47: =ROUND(E46*$B$8,0) -> 2 | D47: =E46-C47 -> 57 | E47: =B47+D47 -> 75 | F47: =ROUND(F46*1.3,0) -> 131 | G47: =F47-E47 -> 56
A48: M20 | B48: =MAX(1,ROUND(E47*0.3,0)) -> 23 | C48: =ROUND(E47*$B$8,0) -> 3 | D48: =E47-C48 -> 72 | E48: =B48+D48 -> 95 | F48: =ROUND(F47*1.3,0) -> 170 | G48: =F48-E48 -> 75
A49: M21 | B49: =MAX(1,ROUND(E48*0.3,0)) -> 29 | C49: =ROUND(E48*$B$8,0) -> 4 | D49: =E48-C49 -> 91 | E49: =B49+D49 -> 120 | F49: =ROUND(F48*1.3,0) -> 221 | G49: =F49-E49 -> 101
A50: M22 | B50: =MAX(1,ROUND(E49*0.3,0)) -> 36 | C50: =ROUND(E49*$B$8,0) -> 5 | D50: =E49-C50 -> 115 | E50: =B50+D50 -> 151 | F50: =ROUND(F49*1.3,0) -> 287 | G50: =F50-E50 -> 136
A51: M23 | B51: =MAX(1,ROUND(E50*0.3,0)) -> 45 | C51: =ROUND(E50*$B$8,0) -> 6 | D51: =E50-C51 -> 145 | E51: =B51+D51 -> 190 | F51: =ROUND(F50*1.3,0) -> 373 | G51: =F51-E51 -> 183
A52: M24 | B52: =MAX(1,ROUND(E51*0.3,0)) -> 57 | C52: =ROUND(E51*$B$8,0) -> 8 | D52: =E51-C52 -> 182 | E52: =B52+D52 -> 239 | F52: =ROUND(F51*1.3,0) -> 485 | G52: =F52-E52 -> 246
A55: CHURN IMPACT SUMMARY
A56: Metric | B56: Without Churn | C56: With Churn | D56: Difference | E56: Impact %
A57: Y1 Ending Carriers (M12) | B57: =F40 -> 21 | C57: =E40 -> 15 | D57: =B57-C57 -> 6 | E57: =IF(B57>0,D57/B57,0) -> 0.28571429
A58: Y2 Ending Carriers (M24) | B58: =F52 -> 485 | C58: =E52 -> 239 | D58: =B58-C58 -> 246 | E58: =IF(B58>0,D58/B58,0) -> 0.50721649
A59: Total Carriers Churned | B59: =Assumptions!B186 -> 0 | C59: =SUM(C29:C52) -> 41 | D59: =C59 -> 41 | E59: carriers lost
A60: Revenue Impact (est.) | B60: =B58*$B$18*12 -> 38138460 | C60: =C58*$B$18*12 -> 18794004 | D60: =B60-C60 -> 19344456 | E60: =IF(B60>0,D60/B60,0) -> 0.50721649
A63: GROWTH RATE JUSTIFICATION - ANNUAL COMPARISONS
A65: Why 430% Year 1 and 260% Year 2 Annual Growth is Achievable:
A67: 1. Y1 Annual Growth (430%): 15% monthly = ~5.3x annual growth from tiny base (4 to ~21 carriers)
A68: 2. Y2 Annual Growth (260%): 30% monthly = ~23x multiplier, but from validated foundation
A69: 3. Market Context: 3.29M annual hires, Y1 captures 0.03% - massive runway remaining
A70: 4. Product-Market Fit: Y1 validates core matching algorithm with real placements
A71: 5. Sales Productivity: Biz Dev hired M3 has 9-month ramp, fully productive in Y2
A72: 6. Referral Engine: 15-20% of new carriers from referrals (built-in viral coefficient)
A73: 7. Network Effects: More drivers = better matches = higher close rates = faster growth
A76: COMPARABLE ANNUAL GROWTH BENCHMARKS (Not Monthly):
A78: Company | B78: Stage | C78: Annual Growth | D78: Context
A79: Uber Freight | B79: Y1-Y2 | C79: 100-150% YoY | D79: Digital freight brokerage expansion
A80: Convoy | B80: Y2-Y3 | C80: 150-300% YoY | D80: During hyper-growth 2017-2019
A81: Loadsmart | B81: Growth phase | C81: 100-150% YoY | D81: AI-powered brokerage scaling
A82: Tenstreet | B82: Established | C82: 20-30% YoY | D82: Market leader, mature growth
A83: Typical B2B SaaS | B83: Post-PMF | C83: 100-200% YoY | D83: Industry benchmark for scaling
A84: VelocityMatch (Target) | B84: Y1 | C84: 430% YoY | D84: From 4 to 21 carriers (tiny base)
A85: VelocityMatch (Target) | B85: Y2 | C85: 260% YoY | D85: From 21 to 76 carriers

Sheet Startup Costs-Led BuildWA
A1: VELOCITYMATCH LAYER 1 STARTUP COSTS - FOUNDER-LED MVP
A2: Strategic Focus: Solo Founder Builds Layer 1 (AI Matching Engine) - Google Cloud Platform
A3: Generated: December 17, 2025
A5: Category | B5: Line Item | C5: Description | D5: Quantity | E5: Unit Cost | F5: Total Cost | G5: Timing | H5: Notes/Assumptions
A6: Technology & Development | B6: Google Cloud Platform - Infrastructure | C6: GCP setup: Compute Engine, Cloud SQL, Cloud Storage, Vertex AI | D6: 1 | E6: =Assumptions!B187 -> 22000 | F6: =Assumptions!B187 -> 22000 | G6: Months 1-6 | H6: GCP for dev/staging/prod + ML infrastructure, founder DevOps
A7: Technology & Development | B7: Mobile Development (Contract) | C7: React Native app for driver onboarding - iOS/Android | D7: 1 | E7: =Assumptions!B188 -> 35000 | F7: =Assumptions!B188 -> 35000 | G7: Months 3-5 | H7: Contractor builds mobile while founder focuses on ML core
A8: Technology & Development | B8: UI/UX Design (Contract) | C8: Design system, driver app UX, carrier dashboard design | D8: 1 | E8: =Assumptions!B189 -> 18000 | F8: =Assumptions!B189 -> 18000 | G8: Months 2-4 | H8: Professional design contractor - founder implements
A9: Technology & Development | B9: AI/ML Training Data & Tools | C9: Synthetic data generation, labeling tools, model training costs | D9: 1 | E9: =Assumptions!B190 -> 8000 | F9: =Assumptions!B190 -> 8000 | G9: Months 1-4 | H9: Data prep for matching algorithm training
A10: Technology & Development | B10: Development Tools & Licenses | C10: GitHub, Linear, Figma, GCP credits, AI/ML tools | D10: 6 | E10: 400 | F10: =Assumptions!B191 -> 2400 | G10: Months 1-6 | H10: Solo founder toolset - lean but professional
A11: Technology & Development | B11: API & Integration Services | C11: Twilio, SendGrid, authentication services, payment processing | D11: 6 | E11: 250 | F11: =Assumptions!B192 -> 1500 | G11: Months 1-6 | H11: Essential third-party services for MVP
A12: Legal & Compliance | B12: Business Formation & Registration | C12: LLC formation, state registration, EIN | D12: 1 | E12: =Assumptions!B193 -> 2000 | F12: =Assumptions!B193 -> 2000 | G12: Month 1 | H12: DIY formation with LegalZoom + attorney review
A13: Legal & Compliance | B13: Freight Broker Authority (MC Number) | C13: FMCSA operating authority, BOC-3 filing | D13: 1 | E13: =Assumptions!B194 -> 2500 | F13: =Assumptions!B194 -> 2500 | G13: Month 1 | H13: Required for freight brokerage operations
A14: Legal & Compliance | B14: Surety Bond | C14: $75k freight broker bond (required by FMCSA) | D14: 1 | E14: =Assumptions!B195 -> 1200 | F14: =Assumptions!B195 -> 1200 | G14: Month 1 | H14: Annual premium ~1.5-2% of bond amount
A15: Legal & Compliance | B15: Business Insurance Package | C15: General liability, cyber liability, E&O bundled | D15: 6 | E15: 650 | F15: =Assumptions!B196 -> 3900 | G15: Months 1-6 | H15: Small business insurance bundle ~$650/month
A16: Legal & Compliance | B16: Legal Templates & Compliance | C16: ToS, Privacy Policy, MSA templates, GDPR/CCPA basics | D16: 1 | E16: =Assumptions!B197 -> 3500 | F16: =Assumptions!B197 -> 3500 | G16: Month 2 | H16: Template package + attorney review - no custom drafting
A17: Legal & Compliance | B17: Trademark Filing (DIY) | C17: USPTO trademark filing for VelocityMatch | D17: 1 | E17: 750 | F17: 750 | G17: Month 2 | H17: DIY filing with online guidance
A18: Pilot Program & Validation | B18: Initial Carrier Outreach | C18: Beta carrier recruitment: LinkedIn, cold outreach, referrals | D18: 1 | E18: =Assumptions!B198 -> 3000 | F18: =Assumptions!B198 -> 3000 | G18: Months 3-5 | H18: Founder-led sales + small incentives for early adopters
A19: Pilot Program & Validation | B19: Driver Recruitment - Organic | C19: Recruit 30-50 drivers: Facebook groups, referrals, job boards | D19: 1 | E19: =Assumptions!B199 -> 5000 | F19: =Assumptions!B199 -> 5000 | G19: Months 4-6 | H19: Organic + minimal paid ads, founder-managed
A20: Pilot Program & Validation | B20: Beta Testing Tools | C20: UserTesting.com, survey tools, feedback management | D20: 1 | E20: =Assumptions!B200 -> 2500 | F20: =Assumptions!B200 -> 2500 | G20: Months 4-6 | H20: DIY user research with affordable tools
A21: Pilot Program & Validation | B21: Market Research & Data | C21: Industry reports, carrier interviews, competitive intel | D21: 1 | E21: =Assumptions!B201 -> 2000 | F21: =Assumptions!B201 -> 2000 | G21: Months 1-2 | H21: Free resources + 1-2 paid reports
A22: Brand & Marketing Foundation | B22: Brand Identity (DIY + Contractor) | C22: Logo design, basic brand guidelines | D22: 1 | E22: =Assumptions!B197 -> 3500 | F22: =Assumptions!B197 -> 3500 | G22: Month 1 | H22: Fiverr/99designs logo + founder creates guidelines
A23: Brand & Marketing Foundation | B23: Website (No-Code) | C23: Webflow/Framer marketing site with lead capture | D23: 1 | E23: =Assumptions!B202 -> 5000 | F23: =Assumptions!B202 -> 5000 | G23: Months 2-3 | H23: No-code platform + founder builds + template
A24: Brand & Marketing Foundation | B24: Sales Deck & Collateral | C24: Pitch deck, one-pager, founder creates in Figma | D24: 1 | E24: =Assumptions!B192 -> 1500 | F24: =Assumptions!B192 -> 1500 | G24: Month 3 | H24: DIY with design template + minor contractor help
A25: Brand & Marketing Foundation | B25: Demo Environment | C25: Sandbox GCP instance with seed data | D25: 1 | E25: =Assumptions!B201 -> 2000 | F25: =Assumptions!B201 -> 2000 | G25: Month 4 | H25: Founder-built demo with scripted scenarios
A26: Brand & Marketing Foundation | B26: Content Creation (Founder) | C26: LinkedIn posts, blog articles, thought leadership | D26: 1 | E26: 500 | F26: 500 | G26: Months 3-6 | H26: Founder writes, Grammarly edits, ChatGPT assists
A27: Operational Infrastructure | B27: Google Cloud Platform (GCP) | C27: Hosting, compute, storage, ML services | D27: 6 | E27: =Assumptions!B203 -> 1200 | F27: =Assumptions!B204 -> 7200 | G27: Months 1-6 | H27: Aggressive use of GCP startup credits + optimization
A28: Operational Infrastructure | B28: Software & Productivity Tools | C28: Notion, Slack free tier, Google Workspace | D28: 6 | E28: 150 | F28: 900 | G28: Months 1-6 | H28: Solo founder using mostly free tiers
A29: Operational Infrastructure | B29: Equipment (Personal) | C29: MacBook Pro upgrade if needed | D29: 1 | E29: =Assumptions!B205 -> 2500 | F29: =Assumptions!B205 -> 2500 | G29: Month 1 | H29: Use existing equipment or minimal upgrade
A30: Operational Infrastructure | B30: Virtual Office | C30: Virtual business address for LLC | D30: 6 | E30: 99 | F30: 594 | G30: Months 1-6 | H30: iPostal1 or similar budget virtual office
A31: Operational Infrastructure | B31: Accounting Software | C31: QuickBooks Self-Employed or Wave (free) | D31: 6 | E31: 30 | F31: 180 | G31: Months 1-6 | H31: DIY bookkeeping with affordable software
A32: Operational Infrastructure | B32: Business Phone | C32: Google Voice or basic VoIP | D32: 6 | E32: 25 | F32: 150 | G32: Months 1-6 | H32: Virtual phone number for professional presence
A33: Founder Living Expenses | B33: Founder Minimal Salary | C33: Bare minimum living expenses during build | D33: 6 | E33: =Assumptions!B197 -> 3500 | F33: =Assumptions!B206 -> 21000 | G33: Months 1-6 | H33: Ramen profitability - cut all non-essentials
A34: Founder Living Expenses | B34: Healthcare (Individual) | C34: Marketplace health insurance or spouse coverage | D34: 6 | E34: 400 | F34: =Assumptions!B207 -> 2400 | G34: Months 1-6 | H34: High-deductible plan to minimize monthly cost
A35: Founder Living Expenses | B35: Payroll Taxes (Self-Employment) | C35: Self-employment tax on minimal salary | D35: 1 | E35: =Assumptions!B208 -> 3300 | F35: =Assumptions!B208 -> 3300 | G35: Months 1-6 | H35: ~15.3% of salary for self-employment tax
A36: Contingency & Reserves | B36: Development Contingency | C36: 10% buffer for technical surprises | D36: 1 | E36: =Assumptions!B209 -> 9000 | F36: =Assumptions!B209 -> 9000 | G36: As Needed | H36: Smaller buffer - founder can pivot quickly
A37: Contingency & Reserves | B37: Emergency Fund | C37: Unexpected expenses or opportunities | D37: 1 | E37: =Assumptions!B210 -> 15000 | F37: =Assumptions!B210 -> 15000 | G37: As Needed | H37: Safety net for critical issues
A39: CATEGORY SUBTOTALS
A40: Technology & Development | F40: =Assumptions!B211 -> 86900
A41: Legal & Compliance | F41: =Assumptions!B212 -> 13850
A42: Pilot Program & Validation | F42: =Assumptions!B213 -> 12500
A43: Brand & Marketing Foundation | F43: =Assumptions!B213 -> 12500
A44: Operational Infrastructure | F44: =Assumptions!B214 -> 11524
A45: Founder Living Expenses | F45: =Assumptions!B215 -> 26700
A46: Contingency & Reserves | F46: =Assumptions!B216 -> 24000
E48: TOTAL STARTUP CAPITAL REQUIRED: | F48: =SUM(F40:F47) -> 187974
A51: KEY ASSUMPTIONS & FOUNDER STRATEGY
A52: Solo Founder Build | B52: You code the entire backend, ML algorithm, carrier dashboard, and integrations
A53: Contract Only Mobile | B53: Hire React Native contractor for mobile app - not your core strength
A54: DIY Everything Else | B54: Legal templates, accounting, marketing, sales - all founder-led
A55: Minimal Living Expenses | B55: $3,500/month survival mode - roommate, rice & beans, no luxuries
A56: 6-Month Timeline | B56: Aggressive build to MVP with validation pilot by Month 6
A57: No Salary Cushion | B57: This assumes you have NO other income and need bare minimum to survive
A58: GCP Startup Credits | B58: Apply for $100K+ in GCP credits to offset infrastructure costs
A59: Technology Stack | B59: Python/Django backend, React carrier dashboard, React Native mobile, GCP
A60: Development Strategy | B60: Backend/ML first (Months 1-3), Mobile contractor parallel (Months 3-5)
A61: Pilot Scale | B61: 2-3 beta carriers, 30-50 drivers - enough to validate matching accuracy
A62: Revenue Timeline | B62: Zero revenue during build - first income Month 7 from pilot carriers
A63: Burn Rate | B63: ~$31,000/month - mostly living expenses + contractors
... A66: Post-MVP Options | B66: (1) Bootstrap to revenue, (2) Raise angel/pre-seed, (3) Pivot based on learnings
A69: FOUNDER REALITY CHECK
A70: Time Commitment | B70: 60-80 hours/week minimum - this is not a side project
A71: Technical Skill Required | B71: You must be comfortable with: Python, ML/AI, React, GCP, DevOps, SQL
A72: No Safety Net | B72: This budget assumes near-zero margin for error - failed contractors hurt
A73: Social Life = Zero | B73: No vacations, minimal socializing, relationships will be tested
A74: Stress Level = Extreme | B74: You are CTO, CEO, designer, marketer, salesperson, and support
A75: Health Risk | B75: Burnout is real - maintain minimal exercise/sleep or you will fail
A76: Alternative Path | B76: If this feels insane, find a technical co-founder or raise $500K seed
A80: STARTUP CAPITAL RECONCILIATION
A82: Category | B82: Amount | C82: Notes
A83: Technology & Development | B83: =Assumptions!B211 -> 86900 | C83: GCP, mobile dev, UI/UX, ML training
A84: Legal & Compliance | B84: =Assumptions!B212 -> 13850 | C84: LLC, MC authority, surety bond, insurance
A85: Pilot Program & Validation | B85: =Assumptions!B213 -> 12500 | C85: Carrier outreach, driver recruitment, beta testing
A86: Brand & Marketing Foundation | B86: =Assumptions!B213 -> 12500 | C86: Brand identity, website, sales collateral
A87: Operational Infrastructure | B87: =Assumptions!B214 -> 11524 | C87: GCP hosting, software tools, equipment
A88: Founder Living Expenses (6 mo) | B88: =Assumptions!B215 -> 26700 | C88: Salary + healthcare + payroll taxes
A89: Contingency & Reserves | B89: =Assumptions!B216 -> 24000 | C89: Dev contingency + emergency fund
A90: TOTAL STARTUP CAPITAL | B90: =SUM(B83:B89) -> 187974 | C90: This is your seed capital requirement

Sheet Revenue Model Overview
A1: VELOCITYMATCH LAYER 1 - REVENUE MODEL
A2: Complete Product & Pricing Structure
A3: Generated: December 22, 2025 | Research-Backed Pricing
B5: Product | C5: Price | D5: Model | E5: Includes | F5: Buyer | G5: Recurring | H5: One-Time
A6: 1 | B6: Matching Engine (Core) | C6: $299/mo | D6: Flat Monthly | E6: AI driver-carrier matching, 10 matches/month included | F6: Carriers, Recruiters | G6: X
A7: 2 | B7: Placement Services | C7: $1,200/placement | D7: Per-Hire Fee | E7: Full-service driver placement, screening, onboarding support | F7: Carriers, Recruiters | H7: X
A8: 3 | B8: Data & Intelligence | C8: $199/mo | D8: Add-On | E8: Market analytics, compensation benchmarking, turnover prediction | F8: Carriers, Recruiters | G8: X
A9: 4 | B9: Brokerage Automation | C9: $399/mo | D9: Flat Monthly | E9: Automated driver-carrier matching for freight brokers | F9: Brokers | G9: X
A10: 5 | B10: Operations Automation | C10: $249/mo | D10: Add-On | E10: Onboarding workflows, DQ file compliance, lightweight dispatch | F10: Carriers | G10: X
A11: 6 | B11: Carrier HR Dashboard | C11: $149/mo | D11: Flat Monthly | E11: Recruiting dashboard, applicant tracking, candidate management | F11: Carriers | G11: X
A12: 7 | B12: Integrations Bundle | C12: $199/mo | D12: Bundle | E12: 3 integrations included (TMS, HRIS/Payroll, ELD connectors) | F12: Carriers | G12: X
A13: 8 | B13: Analytics & Telematics | C13: $499-$999/mo | D13: Tiered | E13: ELD data ingestion, safety scores, driver behavior analytics | F13: Carriers | G13: X
A14: 9 | B14: Enterprise Control Layer | C14: $499/mo | D14: Add-On | E14: Multi-location/fleet mgmt, SSO, admin controls, permissions | F14: Enterprise Carriers | G14: X
A17: TIERED PRICING DETAILS
A19: Analytics & Telematics Tiers
A20: Tier | B20: Fleet Size | C20: Monthly Price | D20: Per-Truck Equivalent
A21: Standard | B21: Up to 100 trucks | C21: $499/mo | D21: $4.99/truck
A22: Professional | B22: 100-250 trucks | C22: $999/mo | D22: $4.00-$9.99/truck
A23: Enterprise | B23: 250+ trucks | C23: Custom | D23: Contact Sales
A26: OVERAGE PRICING (One-Time, As-Needed)
A28: Product | B28: Base Included | C28: Overage Rate | D28: Example
A29: Matching Engine | B29: 10 matches/month | C29: $35/additional match | D29: 15 matches = $299 + (5 x $35) = $474
A30: API Calls | B30: 10,000 calls/month | C30: $0.005/call after limit | D30: 25,000 calls = base + (15K x $0.005) = $75 overage
A31: Analytics & Telematics | B31: Tier truck limit | C31: $8/truck/month beyond tier | D31: Standard tier + 20 extra trucks = $499 + $160 = $659
A34: COST OF GOODS SOLD (COGS)
A36: Product | B36: Variable Cost | C36: Description | D36: Margin
A37: Matching Engine | B37: $15/mo | C37: LLM API costs (OpenAI/Anthropic), compute | D37: 95%
A38: Placement Services | B38: $65/placement | C38: Driver CAC ($46.51) + processing + support | D38: 94.6%
A39: Data & Intelligence | B39: $10/mo | C39: Data storage, third-party data feeds | D39: 95%
A40: Brokerage Automation | B40: $20/mo | C40: API costs, compute | D40: 95%
A41: Operations Automation | B41: $12/mo | C41: Document processing, storage | D41: 95%
A42: Carrier HR Dashboard | B42: $8/mo | C42: Hosting, support allocation | D42: 94.6%
A43: Integrations Bundle | B43: $25/mo | C43: Third-party API fees, maintenance | D43: 87.4%
A44: Analytics & Telematics | B44: $50-$100/mo | C44: ELD API fees, data processing, storage | D44: 80-90%
A45: Enterprise Control Layer | B45: $30/mo | C45: SSO providers, enhanced security | D45: 94%

Sheet Operating Expenses
A1: VELOCITYMATCH - OPERATING EXPENSES MODEL
A2: Dynamic Model - Yellow cells are inputs you can modify
A3: Generated: December 22, 2025
A5: INPUT ASSUMPTIONS
A6: Category | B6: Item | C6: Value | D6: Unit | E6: Notes
A7: Personnel | B7: Founder Monthly Salary | C7: =Assumptions!B217 -> 3500 | D7: $/month | E7: Lean founder salary
A8: Personnel | B8: Biz Dev Base Salary (Annual) | C8: =Assumptions!B218 -> 50000 | D8: $/year | E8: B2B carrier sales + driver retention
A9: Personnel | B9: Biz Dev Commission Rate | C9: 0.12 | D9: % | E9: 12% of first-year carrier revenue
A10: Personnel | B10: Biz Dev Start Month | C10: 3 | D10: month | E10: Staggered hiring
A11: Personnel | B11: Recruiter Hourly Rate | C11: 15 | D11: $/hour | E11: Part-time, you train up
A12: Personnel | B12: Recruiter Hours/Week | C12: 20 | D12: hours | E12: Part-time
A13: Personnel | B13: Recruiter Start Month | C13: 7 | D13: month | E13: Month 6-8 range
A14: Personnel | B14: Contract Dev Hourly Rate | C14: 85 | D14: $/hour | E14: Specialized development
A15: Personnel | B15: Contract Dev Hours/Month | C15: 40 | D15: hours | E15: As needed for key features
A16: Technology | B16: Google Cloud Platform | C16: =Assumptions!B219 -> 1200 | D16: $/month | E16: Compute, storage, ML services
A17: Technology | B17: Third-Party Services | C17: 250 | D17: $/month | E17: Twilio, SendGrid, auth
A18: Technology | B18: Development Tools | C18: 400 | D18: $/month | E18: GitHub, Linear, Figma
A19: Marketing | B19: Carrier Sales/Outreach | C19: =Assumptions!B202 -> 5000 | D19: $/month | E19: LinkedIn Sales Nav, prospecting, trade shows, outreach
A20: Marketing | B20: Driver Marketing | C20: =Assumptions!B220 -> 3000 | D20: $/month | E20: Facebook, job boards, digital ads
A21: G&A | B21: Business Insurance | C21: 650 | D21: $/month | E21: GL, cyber, E&O bundle
A22: G&A | B22: Legal/Compliance | C22: 500 | D22: $/month | E22: Retainer + surety bond amortized
A23: G&A | B23: Virtual Office | C23: 99 | D23: $/month | E23: Business address
A24: G&A | B24: Accounting Software | C24: 30 | D24: $/month | E24: QuickBooks
A25: G&A | B25: Business Phone | C25: 25 | D25: $/month | E25: Google Voice/VoIP
A26: G&A | B26: Healthcare (Founder) | C26: 400 | D26: $/month | E26: High-deductible plan
A27: G&A | B27: Payroll Tax Rate | C27: 0.153 | D27: % | E27: 15.3% self-employment / employer taxes
A30: MONTHLY OPERATING EXPENSES - YEAR 1
A32: Category | B32: Expense Item | C32: M1 | D32: M2 | E32: M3 | F32: M4 | G32: M5 | H32: M6 | I32: M7 | J32: M8 | K32: M9 | L32: M10 | M32: M11 | N32: M12 | O32: Y1 Total
A33: Personnel | B33: Founder Salary | C33: =$C$7 -> 3500 | D33: =$C$7 -> 3500 | E33: =$C$7 -> 3500 | F33: =$C$7 -> 3500 | G33: =$C$7 -> 3500 | H33: =$C$7 -> 3500 | I33: =$C$7 -> 3500 | J33: =$C$7 -> 3500 | ... N33: =$C$7 -> 3500 | O33: =SUM(C33:N33) -> 42000
A34: Personnel | B34: Biz Dev Base | C34: =IFERROR(IF(COLUMN()-2>=$C$10,$C$8/12,0), 0) -> 0 | D34: =IFERROR(IF(COLUMN()-2>=$C$10,$C$8/12,0), 0) -> 0 | E34: =IFERROR(IF(COLUMN()-2>=$C$10,$C$8/12,0), 0) -> 4166.6667 | F34: =IFERROR(IF(COLUMN()-2>=$C$10,$C$8/12,0), 0) -> 4166.6667 | G34: =IFERROR(IF(COLUMN()-2>=$C$10,$C$8/12,0), 0) -> 4166.6667 | H34: =IFERROR(IF(COLUMN()-2>=$C$10,$C$8/12,0), 0) -> 4166.6667 | I34: =IFERROR(IF(COLUMN()-2>=$C$10,$C$8/12,0), 0) -> 4166.6667 | J34: =IFERROR(IF(COLUMN()-2>=$C$10,$C$8/12,0), 0) -> 4166.6667 | ... N34: =IFERROR(IF(COLUMN()-2>=$C$10,$C$8/12,0), 0) -> 4166.6667 | O34: =SUM(C34:N34) -> 41666.667
A35: Personnel | B35: Biz Dev Commission | C35: =0 -> 0 | D35: =0 -> 0 | E35: =0 -> 0 | F35: =0 -> 0 | G35: =0 -> 0 | H35: =0 -> 0 | I35: =0 -> 0 | J35: =0 -> 0 | ... N35: =0 -> 0 | O35: =SUM(C35:N35) -> 0
A36: Personnel | B36: Part-Time Recruiter | C36: =IF(COLUMN()-2>=$C$13,$C$11*$C$12*4,0) -> 0 | D36: =IF(COLUMN()-2>=$C$13,$C$11*$C$12*4,0) -> 0 | E36: =IF(COLUMN()-2>=$C$13,$C$11*$C$12*4,0) -> 0 | F36: =IF(COLUMN()-2>=$C$13,$C$11*$C$12*4,0) -> 0 | G36: =IF(COLUMN()-2>=$C$13,$C$11*$C$12*4,0) -> 0 | H36: =IF(COLUMN()-2>=$C$13,$C$11*$C$12*4,0) -> 0 | I36: =IF(COLUMN()-2>=$C$13,$C$11*$C$12*4,0) -> 1200 | J36: =IF(COLUMN()-2>=$C$13,$C$11*$C$12*4,0) -> 1200 | ... N36: =IF(COLUMN()-2>=$C$13,$C$11*$C$12*4,0) -> 1200 | O36: =SUM(C36:N36) -> 7200
A37: Personnel | B37: Contract Developers | C37: =$C$14*$C$15 -> 3400 | D37: =$C$14*$C$15 -> 3400 | E37: =$C$14*$C$15 -> 3400 | F37: =$C$14*$C$15 -> 3400 | G37: =$C$14*$C$15 -> 3400 | H37: =$C$14*$C$15 -> 3400 | I37: =$C$14*$C$15 -> 3400 | J37: =$C$14*$C$15 -> 3400 | ... N37: =$C$14*$C$15 -> 3400 | O37: =SUM(C37:N37) -> 40800
A38: Personnel | B38: Payroll Taxes | C38: =(C33+C34+C36)*$C$27 -> 535.5 | D38: =(D33+D34+D36)*$C$27 -> 535.5 | E38: =(E33+E34+E36)*$C$27 -> 1173 | F38: =(F33+F34+F36)*$C$27 -> 1173 | G38: =(G33+G34+G36)*$C$27 -> 1173 | H38: =(H33+H34+H36)*$C$27 -> 1173 | I38: =(I33+I34+I36)*$C$27 -> 1356.6 | J38: =(J33+J34+J36)*$C$27 -> 1356.6 | ... N38: =(N33+N34+N36)*$C$27 -> 1356.6 | O38: =SUM(C38:N38) -> 13902.6
A39: Technology | B39: Google Cloud Platform | C39: =$C$16 -> 1200 | D39: =$C$16 -> 1200 | E39: =$C$16 -> 1200 | F39: =$C$16 -> 1200 | G39: =$C$16 -> 1200 | H39: =$C$16 -> 1200 | I39: =$C$16 -> 1200 | J39: =$C$16 -> 1200 | ... N39: =$C$16 -> 1200 | O39: =SUM(C39:N39) -> 14400
A40: Technology | B40: Third-Party Services | C40: =$C$17 -> 250 | D40: =$C$17 -> 250 | E40: =$C$17 -> 250 | F40: =$C$17 -> 250 | G40: =$C$17 -> 250 | H40: =$C$17 -> 250 | I40: =$C$17 -> 250 | J40: =$C$17 -> 250 | ... N40: =$C$17 -> 250 | O40: =SUM(C40:N40) -> 3000
A41: Technology | B41: Development Tools | C41: =$C$18 -> 400 | D41: =$C$18 -> 400 | E41: =$C$18 -> 400 | F41: =$C$18 -> 400 | G41: =$C$18 -> 400 | H41: =$C$18 -> 400 | I41: =$C$18 -> 400 | J41: =$C$18 -> 400 | ... N41: =$C$18 -> 400 | O41: =SUM(C41:N41) -> 4800
A42: Marketing | B42: Carrier Sales/Outreach | C42: =$C$19 -> 5000 | D42: =$C$19 -> 5000 | E42: =$C$19 -> 5000 | F42: =$C$19 -> 5000 | G42: =$C$19 -> 5000 | H42: =$C$19 -> 5000 | I42: =$C$19 -> 5000 | J42: =$C$19 -> 5000 | ... N42: =$C$19 -> 5000 | O42: =SUM(C42:N42) -> 60000
A43: Marketing | B43: Driver Marketing | C43: =$C$20 -> 3000 | D43: =$C$20 -> 3000 | E43: =$C$20 -> 3000 | F43: =$C$20 -> 3000 | G43: =$C$20 -> 3000 | H43: =$C$20 -> 3000 | I43: =$C$20 -> 3000 | J43: =$C$20 -> 3000 | ... N43: =$C$20 -> 3000 | O43: =SUM(C43:N43) -> 36000
A44: G&A | B44: Business Insurance | C44: =$C$21 -> 650 | D44: =$C$21 -> 650 | E44: =$C$21 -> 650 | F44: =$C$21 -> 650 | G44: =$C$21 -> 650 | H44: =$C$21 -> 650 | I44: =$C$21 -> 650 | J44: =$C$21 -> 650 | ... N44: =$C$21 -> 650 | O44: =SUM(C44:N44) -> 7800
A45: G&A | B45: Legal/Compliance | C45: =$C$22 -> 500 | D45: =$C$22 -> 500 | E45: =$C$22 -> 500 | F45: =$C$22 -> 500 | G45: =$C$22 -> 500 | H45: =$C$22 -> 500 | I45: =$C$22 -> 500 | J45: =$C$22 -> 500 | ... N45: =$C$22 -> 500 | O45: =SUM(C45:N45) -> 6000
A46: G&A | B46: Virtual Office | C46: =$C$23 -> 99 | D46: =$C$23 -> 99 | E46: =$C$23 -> 99 | F46: =$C$23 -> 99 | G46: =$C$23 -> 99 | H46: =$C$23 -> 99 | I46: =$C$23 -> 99 | J46: =$C$23 -> 99 | ... N46: =$C$23 -> 99 | O46: =SUM(C46:N46) -> 1188
A47: G&A | B47: Accounting Software | C47: =$C$24 -> 30 | D47: =$C$24 -> 30 | E47: =$C$24 -> 30 | F47: =$C$24 -> 30 | G47: =$C$24 -> 30 | H47: =$C$24 -> 30 | I47: =$C$24 -> 30 | J47: =$C$24 -> 30 | ... N47: =$C$24 -> 30 | O47: =SUM(C47:N47) -> 360
A48: G&A | B48: Business Phone | C48: =$C$25 -> 25 | D48: =$C$25 -> 25 | E48: =$C$25 -> 25 | F48: =$C$25 -> 25 | G48: =$C$25 -> 25 | H48: =$C$25 -> 25 | I48: =$C$25 -> 25 | J48: =$C$25 -> 25 | ... N48: =$C$25 -> 25 | O48: =SUM(C48:N48) -> 300
A49: G&A | B49: Healthcare (Founder) | C49: =$C$26 -> 400 | D49: =$C$26 -> 400 | E49: =$C$26 -> 400 | F49: =$C$26 -> 400 | G49: =$C$26 -> 400 | H49: =$C$26 -> 400 | I49: =$C$26 -> 400 | J49: =$C$26 -> 400 | ... N49: =$C$26 -> 400 | O49: =SUM(C49:N49) -> 4800
B51: PERSONNEL SUBTOTAL | C51: =SUM(C33:C38) -> 7435.5 | D51: =SUM(D33:D38) -> 7435.5 | E51: =SUM(E33:E38) -> 12239.667 | F51: =SUM(F33:F38) -> 12239.667 | G51: =SUM(G33:G38) -> 12239.667 | H51: =SUM(H33:H38) -> 12239.667 | I51: =SUM(I33:I38) -> 13623.267 | J51: =SUM(J33:J38) -> 13623.267 | ... N51: =SUM(N33:N38) -> 13623.267 | O51: =SUM(C51:N51) -> 145569.27
B52: TECHNOLOGY SUBTOTAL | C52: =SUM(C39:C41) -> 1850 | D52: =SUM(D39:D41) -> 1850 | E52: =SUM(E39:E41) -> 1850 | F52: =SUM(F39:F41) -> 1850 | G52: =SUM(G39:G41) -> 1850 | H52: =SUM(H39:H41) -> 1850 | I52: =SUM(I39:I41) -> 1850 | J52: =SUM(J39:J41) -> 1850 | ... N52: =SUM(N39:N41) -> 1850 | O52: =SUM(C52:N52) -> 22200
B53: MARKETING SUBTOTAL | C53: =SUM(C42:C43) -> 8000 | D53: =SUM(D42:D43) -> 8000 | E53: =SUM(E42:E43) -> 8000 | F53: =SUM(F42:F43) -> 8000 | G53: =SUM(G42:G43) -> 8000 | H53: =SUM(H42:H43) -> 8000 | I53: =SUM(I42:I43) -> 8000 | J53: =SUM(J42:J43) -> 8000 | ... N53: =SUM(N42:N43) -> 8000 | O53: =SUM(C53:N53) -> 96000
B54: G&A SUBTOTAL | C54: =SUM(C44:C49) -> 1704 | D54: =SUM(D44:D49) -> 1704 | E54: =SUM(E44:E49) -> 1704 | F54: =SUM(F44:F49) -> 1704 | G54: =SUM(G44:G49) -> 1704 | H54: =SUM(H44:H49) -> 1704 | I54: =SUM(I44:I49) -> 1704 | J54: =SUM(J44:J49) -> 1704 | ... N54: =SUM(N44:N49) -> 1704 | O54: =SUM(C54:N54) -> 20448
B56: TOTAL MONTHLY OPEX | C56: =C51+C52+C53+C54 -> 18989.5 | D56: =D51+D52+D53+D54 -> 18989.5 | E56: =E51+E52+E53+E54 -> 23793.667 | F56: =F51+F52+F53+F54 -> 23793.667 | G56: =G51+G52+G53+G54 -> 23793.667 | H56: =H51+H52+H53+H54 -> 23793.667 | I56: =I51+I52+I53+I54 -> 25177.267 | J56: =J51+J52+J53+J54 -> 25177.267 | ... N56: =N51+N52+N53+N54 -> 25177.267 | O56: =SUM(C56:N56) -> 284217.27
A60: ALIGNMENT WITH STARTUP COSTS
A62: Note: Monthly operating expenses here represent ongoing costs AFTER the 6-month startup phase.
A63: Startup Costs sheet covers one-time and initial 6-month costs. This sheet models Month 1+ operations.
A65: Key Alignment Points:
A66: - Founder Salary: $3,500/mo matches both sheets
A67: - GCP: $1,200/mo matches both sheets
A68: - Marketing: $5K carrier + $3K driver = $8K total monthly marketing budget
A69: - Biz Dev hire: Not in Startup (6-mo solo), starts Month 3 in OpEx

Sheet P&L
A1: VELOCITYMATCH - PROFIT & LOSS STATEMENT
A2: 24-Month Projection | Yellow cells are modifiable inputs
A3: Generated: December 22, 2025
A4: NOTE: Active Carriers now pulled from Churn Model (includes churn impact)
A5: REVENUE ASSUMPTIONS
A6: Input | B6: Value | C6: Unit | D6: Notes
A7: Starting Carriers (Month 1) | B7: =Assumptions!B221 -> 4 | C7: carriers | D7: Initial beta customers
A8: Monthly Carrier Growth Rate (Y1) | B8: =Assumptions!B161 -> 0.15 | C8: % | D8: 15% month-over-month growth
A9: Monthly Carrier Growth Rate (Y2) | B9: =Assumptions!B222 -> 0.3 | C9: % | D9: 20% month-over-month growth
A10: Placements per Carrier per Month | B10: 5 | C10: placements | D10: Avg placements per active carrier
A11: Matching Engine Price | B11: =Assumptions!B172 -> 299 | C11: $/month | D11: Core subscription
A12: Placement Fee | B12: =Assumptions!B219 -> 1200 | C12: $/placement | D12: Per successful hire
A13: Add-on Attach Rate | B13: 0.6 | C13: % | D13: 25% of carriers buy add-ons after M3
A14: Avg Add-on Revenue per Carrier | B14: 400 | C14: $/month | D14: Blended avg of add-on products
A15: Overage Revenue per Carrier | B15: 70 | C15: $/month | D15: Avg overage (extra matches)
A16: Overage Adoption Rate | B16: =Assumptions!B169 -> 0.2 | C16: % | D16: 20% of carriers use overages
A18: COGS ASSUMPTIONS
A19: Input | B19: Value | C19: Unit | D19: Notes
A20: Matching Engine COGS | B20: 15 | C20: $/month/carrier | D20: LLM API, compute
A21: Placement COGS | B21: 65 | C21: $/placement | D21: Driver CAC + processing
A22: Add-on COGS % | B22: 0.1 | C22: % | D22: 10% of add-on revenue
A25: PROFIT & LOSS - 24 MONTH PROJECTION
C26: YEAR 1 | O26: YEAR 2
A27: Category | B27: Line Item | C27: M1 | D27: M2 | E27: M3 | F27: M4 | G27: M5 | H27: M6 | I27: M7 | J27: M8 | K27: M9 | L27: M10 | M27: M11 | N27: M12 | O27: M13 | P27: M14 | Q27: M15 | R27: M16 | S27: M17 | T27: M18 | U27: M19 | V27: M20 | W27: M21 | X27: M22 | Y27: M23 | Z27: M24 | AA27: Y1 Total | AB27: Y2 Total
A28: Metrics | B28: Active Carriers | C28: ='Churn Model'!E29 -> 4 | D28: ='Churn Model'!E30 -> 5 | E28: ='Churn Model'!E31 -> 6 | F28: ='Churn Model'!E32 -> 7 | G28: ='Churn Model'!E33 -> 8 | H28: ='Churn Model'!E34 -> 9 | I28: ='Churn Model'!E35 -> 10 | J28: ='Churn Model'!E36 -> 11 | K28: ='Churn Model'!E37 -> 12 | L28: ='Churn Model'!E38 -> 13 | M28: ='Churn Model'!E39 -> 14 | N28: ='Churn Model'!E40 -> 15 | O28: ='Churn Model'!E41 -> 19 | P28: ='Churn Model'!E42 -> 24 | Q28: ='Churn Model'!E43 -> 30 | R28: ='Churn Model'!E44 -> 38 | S28: ='Churn Model'!E45 -> 47 | T28: ='Churn Model'!E46 -> 59 | U28: ='Churn Model'!E47 -> 75 | V28: ='Churn Model'!E48 -> 95 | W28: ='Churn Model'!E49 -> 120 | X28: ='Churn Model'!E50 -> 151 | Y28: ='Churn Model'!E51 -> 190 | Z28: ='Churn Model'!E52 -> 239 | AA28: ='Churn Model'!E40 -> 15 | AB28: ='Churn Model'!E52 -> 239
A29: Revenue | B29: Matching Engine | C29: =C28*$B$11 -> 1196 | D29: =D28*$B$11 -> 1495 | E29: =E28*$B$11 -> 1794 | F29: =F28*$B$11 -> 2093 | G29: =G28*$B$11 -> 2392 | H29: =H28*$B$11 -> 2691 | I29: =I28*$B$11 -> 2990 | J29: =J28*$B$11 -> 3289 | ... Z29: =Z28*$B$11 -> 71461 | AA29: =SUM(C29:N29) -> 34086 | AB29: =SUM(O29:Z29) -> 325013
A30: Revenue | B30: Placement Services | C30: =C28*$B$10*$B$12 -> 24000 | D30: =D28*$B$10*$B$12 -> 30000 | E30: =E28*$B$10*$B$12 -> 36000 | F30: =F28*$B$10*$B$12 -> 42000 | G30: =G28*$B$10*$B$12 -> 48000 | H30: =H28*$B$10*$B$12 -> 54000 | I30: =I28*$B$10*$B$12 -> 60000 | J30: =J28*$B$10*$B$12 -> 66000 | ... Z30: =Z28*$B$10*$B$12 -> 1434000 | AA30: =SUM(C30:N30) -> 684000 | AB30: =SUM(O30:Z30) -> 6522000
A31: Revenue | B31: Add-on Products | C31: 0 | D31: 0 | E31: 0 | F31: =F28*$B$13*$B$14 -> 1680 | G31: =G28*$B$13*$B$14 -> 1920 | H31: =H28*$B$13*$B$14 -> 2160 | I31: =I28*$B$13*$B$14 -> 2400 | J31: =J28*$B$13*$B$14 -> 2640 | K31: =K28*$B$13*$B$14 -> 2880 | L31: =L28*$B$13*$B$14 -> 3120 | M31: =M28*$B$13*$B$14 -> 3360 | ... Z31: =Z28*$B$13*$B$14 -> 57360 | AA31: =SUM(C31:N31) -> 23760 | AB31: =SUM(O31:Z31) -> 260880
A32: Revenue | B32: Overage Revenue | C32: =C28*$B$16*$B$15 -> 56 | D32: =D28*$B$16*$B$15 -> 70 | E32: =E28*$B$16*$B$15 -> 84 | F32: =F28*$B$16*$B$15 -> 98 | G32: =G28*$B$16*$B$15 -> 112 | H32: =H28*$B$16*$B$15 -> 126 | I32: =I28*$B$16*$B$15 -> 140 | J32: =J28*$B$16*$B$15 -> 154 | ... Z32: =Z28*$B$16*$B$15 -> 3346 | AA32: =SUM(C32:N32) -> 1596 | AB32: =SUM(O32:Z32) -> 15218
A33: Revenue | B33: TOTAL REVENUE | C33: =SUM(C29:C32) -> 25252 | D33: =SUM(D29:D32) -> 31565 | E33: =SUM(E29:E32) -> 37878 | F33: =SUM(F29:F32) -> 45871 | G33: =SUM(G29:G32) -> 52424 | H33: =SUM(H29:H32) -> 58977 | I33: =SUM(I29:I32) -> 65530 | J33: =SUM(J29:J32) -> 72083 | ... Z33: =SUM(Z29:Z32) -> 1566167 | AA33: =SUM(C33:N33) -> 743442 | AB33: =SUM(O33:Z33) -> 7123111
A34: COGS | B34: Matching Engine COGS | C34: =C28*$B$20 -> 60 | D34: =D28*$B$20 -> 75 | E34: =E28*$B$20 -> 90 | F34: =F28*$B$20 -> 105 | G34: =G28*$B$20 -> 120 | H34: =H28*$B$20 -> 135 | I34: =I28*$B$20 -> 150 | J34: =J28*$B$20 -> 165 | ... Z34: =Z28*$B$20 -> 3585 | AA34: =SUM(C34:N34) -> 1710 | AB34: =SUM(O34:Z34) -> 16305
A35: COGS | B35: Placement COGS | C35: =C28*$B$10*$B$21 -> 1300 | D35: =D28*$B$10*$B$21 -> 1625 | E35: =E28*$B$10*$B$21 -> 1950 | F35: =F28*$B$10*$B$21 -> 2275 | G35: =G28*$B$10*$B$21 -> 2600 | H35: =H28*$B$10*$B$21 -> 2925 | I35: =I28*$B$10*$B$21 -> 3250 | J35: =J28*$B$10*$B$21 -> 3575 | ... Z35: =Z28*$B$10*$B$21 -> 77675 | AA35: =SUM(C35:N35) -> 37050 | AB35: =SUM(O35:Z35) -> 353275
A36: COGS | B36: Add-on COGS | C36: =C31*$B$22 -> 0 | D36: =D31*$B$22 -> 0 | E36: =E31*$B$22 -> 0 | F36: =F31*$B$22 -> 168 | G36: =G31*$B$22 -> 192 | H36: =H31*$B$22 -> 216 | I36: =I31*$B$22 -> 240 | J36: =J31*$B$22 -> 264 | ... Z36: =Z31*$B$22 -> 5736 | AA36: =SUM(C36:N36) -> 2376 | AB36: =SUM(O36:Z36) -> 26088
A37: COGS | B37: TOTAL COGS | C37: =SUM(C34:C36) -> 1360 | D37: =SUM(D34:D36) -> 1700 | E37: =SUM(E34:E36) -> 2040 | F37: =SUM(F34:F36) -> 2548 | G37: =SUM(G34:G36) -> 2912 | H37: =SUM(H34:H36) -> 3276 | I37: =SUM(I34:I36) -> 3640 | J37: =SUM(J34:J36) -> 4004 | ... Z37: =SUM(Z34:Z36) -> 86996 | AA37: =SUM(C37:N37) -> 41136 | AB37: =SUM(O37:Z37) -> 395668
A38: Profit | B38: GROSS PROFIT | C38: =C33-C37 -> 23892 | D38: =D33-D37 -> 29865 | E38: =E33-E37 -> 35838 | F38: =F33-F37 -> 43323 | G38: =G33-G37 -> 49512 | H38: =H33-H37 -> 55701 | I38: =I33-I37 -> 61890 | J38: =J33-J37 -> 68079 | ... Z38: =Z33-Z37 -> 1479171 | AA38: =SUM(C38:N38) -> 702306 | AB38: =SUM(O38:Z38) -> 6727443
A39: Profit | B39: Gross Margin % | C39: =IFERROR(IF(C33=0,0,C38/C33), 0) -> 0.94614288 | D39: =IFERROR(IF(D33=0,0,D38/D33), 0) -> 0.94614288 | E39: =IFERROR(IF(E33=0,0,E38/E33), 0) -> 0.94614288 | F39: =IFERROR(IF(F33=0,0,F38/F33), 0) -> 0.94445292 | G39: =IFERROR(IF(G33=0,0,G38/G33), 0) -> 0.94445292 | H39: =IFERROR(IF(H33=0,0,H38/H33), 0) -> 0.94445292 | I39: =IFERROR(IF(I33=0,0,I38/I33), 0) -> 0.94445292 | J39: =IFERROR(IF(J33=0,0,J38/J33), 0) -> 0.94445292 | ... Z39: =IFERROR(IF(Z33=0,0,Z38/Z33), 0) -> 0.94445292 | AA39: =AVERAGE(C39:N39) -> 0.94487541 | AB39: =AVERAGE(O39:Z39) -> 0.94445292
A40: OpEx | B40: Operating Expenses | C40: ='Operating Expenses'!C56 -> 18989.5 | D40: ='Operating Expenses'!D56 -> 18989.5 | E40: ='Operating Expenses'!E56 -> 23793.667 | F40: ='Operating Expenses'!F56 -> 23793.667 | G40: ='Operating Expenses'!G56 -> 23793.667 | H40: ='Operating Expenses'!H56 -> 23793.667 | I40: ='Operating Expenses'!I56 -> 25177.267 | J40: ='Operating Expenses'!J56 -> 25177.267 | ... N40: ='Operating Expenses'!N56 -> 25177.267 | O40: ='Operating Expenses'!N56*1.1 -> 27694.993 | P40: ='Operating Expenses'!N56*1.1 -> 27694.993 | Q40: ='Operating Expenses'!N56*1.1 -> 27694.993 | R40: ='Operating Expenses'!N56*1.1 -> 27694.993 | S40: ='Operating Expenses'!N56*1.1 -> 27694.993 | T40: ='Operating Expenses'!N56*1.1 -> 27694.993 | U40: ='Operating Expenses'!N56*1.1 -> 27694.993 | V40: ='Operating Expenses'!N56*1.1 -> 27694.993 | W40: ='Operating Expenses'!N56*1.1 -> 27694.993 | X40: ='Operating Expenses'!N56*1.1 -> 27694.993 | Y40: ='Operating Expenses'!N56*1.1 -> 27694.993 | Z40: ='Operating Expenses'!N56*1.1 -> 27694.993 | AA40: =SUM(C40:N40) -> 284217.27 | AB40: =SUM(O40:Z40) -> 332339.92
A41: Profit | B41: NET PROFIT (EBITDA) | C41: =C38-C40 -> 4902.5 | D41: =D38-D40 -> 10875.5 | E41: =E38-E40 -> 12044.333 | F41: =F38-F40 -> 19529.333 | G41: =G38-G40 -> 25718.333 | H41: =H38-H40 -> 31907.333 | I41: =I38-I40 -> 36712.733 | J41: =J38-J40 -> 42901.733 | ... Z41: =Z38-Z40 -> 1451476 | AA41: =SUM(C41:N41) -> 418088.73 | AB41: =SUM(O41:Z41) -> 6395103.1
A42: Profit | B42: Net Margin % | C42: =IFERROR(IF(C33=0,0,C41/C33), 0) -> 0.19414304 | D42: =IFERROR(IF(D33=0,0,D41/D33), 0) -> 0.34454301 | E42: =IFERROR(IF(E33=0,0,E41/E33), 0) -> 0.31797701 | F42: =IFERROR(IF(F33=0,0,F41/F33), 0) -> 0.42574466 | G42: =IFERROR(IF(G33=0,0,G41/G33), 0) -> 0.49058319 | H42: =IFERROR(IF(H33=0,0,H41/H33), 0) -> 0.54101316 | I42: =IFERROR(IF(I33=0,0,I41/I33), 0) -> 0.56024315 | J42: =IFERROR(IF(J33=0,0,J41/J33), 0) -> 0.59517131 | ... Z42: =IFERROR(IF(Z33=0,0,Z41/Z33), 0) -> 0.92676963 | AA42: =AVERAGE(C42:N42) -> 0.50841117 | AB42: =AVERAGE(O42:Z42) -> 0.85977326
A45: KEY METRICS SUMMARY
A47: Metric | B47: Year 1 | C47: Year 2 | D47: Notes
A48: Total Revenue | B48: =AA33 -> 743442 | C48: =C33 -> 25252 | D48: All revenue streams
A49: Total COGS | B49: =AA37 -> 41136 | C49: =AB37 -> 395668 | D49: Variable costs
A50: Gross Profit | B50: =AA38 -> 702306 | C50: =C38 -> 23892 | D50: Revenue - COGS
A51: Avg Gross Margin | B51: =AA39 -> 0.94487541 | C51: =AB39 -> 0.94445292 | D51: Gross Profit / Revenue
A52: Operating Expenses | B52: =AA40 -> 284217.27 | C52: =C40 -> 18989.5 | D52: From OpEx sheet
A53: Net Profit (EBITDA) | B53: =AA41 -> 418088.73 | C53: =C41 -> 4902.5 | D53: Gross Profit - OpEx
A54: Avg Net Margin | B54: =AA42 -> 0.50841117 | C54: =AB42 -> 0.85977326 | D54: Net Profit / Revenue
A55: NOTE ON STARTUP COSTS | B55: =AA28 -> 15 | C55: =AB28 -> 239 | D55: Active subscribers
A56: Startup costs are reflected in Cash Flow sheet as initial capital required.
A57: Total Startup Capital: ='Startup Costs-Led BuildWA'!B90

Sheet Cash Flow
A1: VELOCITYMATCH - CASH FLOW STATEMENT
A2: 24-Month Projection | Tracks cash position and runway
A3: Generated: December 22, 2025
A5: CASH ASSUMPTIONS
A6: Input | B6: Value | C6: Unit | D6: Notes
A7: Starting Cash (Seed Capital) | B7: ='Startup Costs-Led BuildWA'!B90 -> 187974 | C7: $ | D7: Linked to Startup Costs sheet
A8: Accounts Receivable Days | B8: 30 | C8: days | D8: Avg days to collect payment
A9: Collection Rate | B9: 0.95 | C9: % | D9: 95% of revenue collected (5% bad debt)
A12: CASH FLOW STATEMENT - 24 MONTHS
C13: YEAR 1 | O13: YEAR 2
A14: Section | B14: Line Item | C14: M1 | D14: M2 | E14: M3 | F14: M4 | G14: M5 | H14: M6 | I14: M7 | J14: M8 | K14: M9 | L14: M10 | M14: M11 | N14: M12 | O14: M13 | P14: M14 | Q14: M15 | R14: M16 | S14: M17 | T14: M18 | U14: M19 | V14: M20 | W14: M21 | X14: M22 | Y14: M23 | Z14: M24 | AA14: Y1 Total | AB14: Y2 Total
A15: Beginning | B15: Cash at Start of Period | C15: =$B$7 -> 187974 | D15: =C24 -> 92624.5 | E15: =D24 -> 95924.4 | F15: =E24 -> 100077.48 | G15: =F24 -> 109719.92 | H15: =G24 -> 126591.7 | I15: =H24 -> 149324.83 | J15: =I24 -> 176535.72 | K15: =J24 -> 209607.95 | ... Z15: =Y24 -> 3976854 | AA15: =N15 -> 343992.75 | AB15: =Z15 -> 3976854
A16: Inflows | B16: Revenue Collected | C16: 0 | D16: ='P&L'!C33*$B$9 -> 23989.4 | E16: ='P&L'!D33*$B$9 -> 29986.75 | F16: ='P&L'!E33*$B$9 -> 35984.1 | G16: ='P&L'!F33*$B$9 -> 43577.45 | H16: ='P&L'!G33*$B$9 -> 49802.8 | I16: ='P&L'!H33*$B$9 -> 56028.15 | J16: ='P&L'!I33*$B$9 -> 62253.5 | K16: ='P&L'!J33*$B$9 -> 68478.85 | ... Z16: ='P&L'!Y33*$B$9 -> 1182816.5 | AA16: =SUM(C16:N16) -> 612889.65 | AB16: =SUM(O16:Z16) -> 5372477.1
A17: Inflows | B17: Outside Investment | C17: 0 | D17: 0 | E17: 0 | F17: 0 | G17: 0 | H17: 0 | I17: 0 | J17: 0 | K17: 0 | L17: 0 | M17: 0 | N17: 0 | O17: 0 | P17: 0 | Q17: 0 | R17: 0 | S17: 0 | T17: 0 | U17: 0 | V17: 0 | W17: 0 | X17: 0 | Y17: 0 | Z17: 0 | AA17: =SUM(C17:N17) -> 0 | AB17: =SUM(O17:Z17) -> 0
A18: Inflows | B18: TOTAL CASH INFLOWS | C18: =C16+C17 -> 0 | D18: =D16+D17 -> 23989.4 | E18: =E16+E17 -> 29986.75 | F18: =F16+F17 -> 35984.1 | G18: =G16+G17 -> 43577.45 | H18: =H16+H17 -> 49802.8 | I18: =I16+I17 -> 56028.15 | J18: =J16+J17 -> 62253.5 | ... Z18: =Z16+Z17 -> 1182816.5 | AA18: =SUM(C18:N18) -> 612889.65 | AB18: =SUM(O18:Z18) -> 5372477.1
A19: Outflows | B19: COGS Paid | C19: ='P&L'!C37 -> 1360 | D19: ='P&L'!D37 -> 1700 | E19: ='P&L'!E37 -> 2040 | F19: ='P&L'!F37 -> 2548 | G19: ='P&L'!G37 -> 2912 | H19: ='P&L'!H37 -> 3276 | I19: ='P&L'!I37 -> 3640 | J19: ='P&L'!J37 -> 4004 | ... Z19: ='P&L'!Z37 -> 86996 | AA19: =SUM(C19:N19) -> 41136 | AB19: =SUM(O19:Z19) -> 395668
A20: Outflows | B20: Operating Expenses | C20: ='P&L'!C40 -> 18989.5 | D20: ='P&L'!D40 -> 18989.5 | E20: ='P&L'!E40 -> 23793.667 | F20: ='P&L'!F40 -> 23793.667 | G20: ='P&L'!G40 -> 23793.667 | H20: ='P&L'!H40 -> 23793.667 | I20: ='P&L'!I40 -> 25177.267 | J20: ='P&L'!J40 -> 25177.267 | ... Z20: ='P&L'!Z40 -> 27694.993 | AA20: =SUM(C20:N20) -> 284217.27 | AB20: =SUM(O20:Z20) -> 332339.92
A21: Outflows | B21: Startup Costs (M1 only) | C21: =Assumptions!B223 -> 75000 | D21: 0 | E21: 0 | F21: 0 | G21: 0 | H21: 0 | I21: 0 | J21: 0 | K21: 0 | L21: 0 | M21: 0 | N21: 0 | O21: 0 | P21: 0 | Q21: 0 | R21: 0 | S21: 0 | T21: 0 | U21: 0 | V21: 0 | W21: 0 | X21: 0 | Y21: 0 | Z21: 0 | AA21: =SUM(C21:N21) -> 75000 | AB21: =SUM(O21:Z21) -> 0
A22: Outflows | B22: TOTAL CASH OUTFLOWS | C22: =C19+C20+C21 -> 95349.5 | D22: =D19+D20+D21 -> 20689.5 | E22: =E19+E20+E21 -> 25833.667 | F22: =F19+F20+F21 -> 26341.667 | G22: =G19+G20+G21 -> 26705.667 | H22: =H19+H20+H21 -> 27069.667 | I22: =I19+I20+I21 -> 28817.267 | J22: =J19+J20+J21 -> 29181.267 | ... Z22: =Z19+Z20+Z21 -> 114690.99 | AA22: =SUM(C22:N22) -> 400353.27 | AB22: =SUM(O22:Z22) -> 728007.92
A23: Net | B23: NET CASH FLOW | C23: =C18-C22 -> -95349.5 | D23: =D18-D22 -> 3299.9 | E23: =E18-E22 -> 4153.0833 | F23: =F18-F22 -> 9642.4333 | G23: =G18-G22 -> 16871.783 | H23: =H18-H22 -> 22733.133 | I23: =I18-I22 -> 27210.883 | J23: =J18-J22 -> 33072.233 | ... Z23: =Z18-Z22 -> 1068125.5 | AA23: =SUM(C23:N23) -> 212536.38 | AB23: =SUM(O23:Z23) -> 4644469.1
A24: Ending | B24: Cash at End of Period | C24: =C15+C23 -> 92624.5 | D24: =D15+D23 -> 95924.4 | E24: =E15+E23 -> 100077.48 | F24: =F15+F23 -> 109719.92 | G24: =G15+G23 -> 126591.7 | H24: =H15+H23 -> 149324.83 | I24: =I15+I23 -> 176535.72 | J24: =J15+J23 -> 209607.95 | ... Z24: =Z15+Z23 -> 5044979.5 | AA24: =N24 -> 400510.38 | AB24: =Z24 -> 5044979.5
A25: Metrics | B25: Cumulative Cash Burn | C25: =IF(C23<0,ABS(C23),0) -> 95349.5 | D25: =C25+IF(D23<0,ABS(D23),0) -> 95349.5 | E25: =D25+IF(E23<0,ABS(E23),0) -> 95349.5 | F25: =E25+IF(F23<0,ABS(F23),0) -> 95349.5 | G25: =F25+IF(G23<0,ABS(G23),0) -> 95349.5 | H25: =G25+IF(H23<0,ABS(H23),0) -> 95349.5 | I25: =H25+IF(I23<0,ABS(I23),0) -> 95349.5 | J25: =I25+IF(J23<0,ABS(J23),0) -> 95349.5 | K25: =J25+IF(K23<0,ABS(K23),0) -> 95349.5 | ... Z25: =Y25+IF(Z23<0,ABS(Z23),0) -> 95349.5 | AA25: =N25 -> 95349.5 | AB25: =Z25 -> 95349.5
A26: Metrics | B26: Months of Runway | C26: =IFERROR(IF(C20=0,99,C24/C20), 0) -> 4.8776692 | D26: =IFERROR(IF(D20=0,99,D24/D20), 0) -> 5.0514442 | E26: =IFERROR(IF(E20=0,99,E24/E20), 0) -> 4.2060555 | F26: =IFERROR(IF(AVERAGE(D22:F22)=0,99,F24/AVERAGE(D22:F22)), 0) -> 4.5174021 | G26: =IFERROR(IF(AVERAGE(E22:G22)=0,99,G24/AVERAGE(E22:G22)), 0) -> 4.814532 | H26: =IFERROR(IF(AVERAGE(F22:H22)=0,99,H24/AVERAGE(F22:H22)), 0) -> 5.5915037 | I26: =IFERROR(IF(AVERAGE(G22:I22)=0,99,I24/AVERAGE(G22:I22)), 0) -> 6.4122833 | J26: =IFERROR(IF(AVERAGE(H22:J22)=0,99,J24/AVERAGE(H22:J22)), 0) -> 7.3919967 | K26: =IFERROR(IF(AVERAGE(I22:K22)=0,99,K24/AVERAGE(I22:K22)), 0) -> 8.5171606 | L26: =IFERROR(IF(AVERAGE(J22:L22)=0,99,L24/AVERAGE(J22:L22)), 0) -> 9.9283743 | M26: =IFERROR(IF(AVERAGE(K22:M22)=0,99,M24/AVERAGE(K22:M22)), 0) -> 11.50121 | ... Z26: =IFERROR(IF(AVERAGE(X22:Z22)=0,99,Z24/AVERAGE(X22:Z22)), 0) -> 51.443516 | AA26: =N26 -> 13.229837 | AB26: =Z26 -> 51.443516
A30: CASH POSITION SUMMARY
A32: Metric | B32: Value | C32: Notes
A33: Starting Capital | B33: =$B$7 -> 187974 | C33: Seed funding
A34: Y1 Total Cash Inflows | B34: =AA18 -> 612889.65 | C34: Revenue collected + investment
A35: Y1 Total Cash Outflows | B35: =AA22 -> 400353.27 | C35: COGS + OpEx + Startup
A36: Y1 Net Cash Flow | B36: =AA23 -> 212536.38 | C36: Inflows - Outflows
A37: Y1 Ending Cash | B37: =N24 -> 400510.38 | C37: Cash position end of Y1
A38: Y2 Net Cash Flow | B38: =AB23 -> 4644469.1 | C38: Year 2 net
A39: Y2 Ending Cash | B39: =Z24 -> 5044979.5 | C39: Cash position end of Y2
A40: Break-Even Month | B40: =IFERROR(MATCH(TRUE,INDEX(C23:Z23>0,0),0), 0) -> 2 | C40: First month with positive net cash flow

Sheet Balance Sheet
A1: VELOCITYMATCH - BALANCE SHEET
A2: Pro Forma Balance Sheet | End of Year Snapshots
A3: Generated: December 23, 2025 | Full Accrual Model with AR/AP
A5: Category | B5: Line Item | C5: Start (M0) | D5: End Y1 (M12) | E5: End Y2 (M24) | F5: Notes
B6: ASSETS
A7: Current Assets | B7: Cash & Cash Equivalents | C7: ='Startup Costs-Led BuildWA'!B90 -> 187974 | D7: ='Cash Flow'!N24 -> 400510.38 | E7: ='Cash Flow'!Z24 -> 5044979.5 | F7: From Cash Flow sheet (Y1/Y2) or Startup Capital (Start)
A8: Current Assets | B8: Accounts Receivable | C8: 0 | D8: =IFERROR('P&L'!N33/12, "N/A") -> 8191.25 | E8: =IFERROR('P&L'!Z33/12, "N/A") -> 130513.92 | F8: 1 month of revenue outstanding (30-day terms)
A9: Current Assets | B9: Prepaid Expenses | C9: 0 | D9: =Assumptions!B224 -> 2000 | E9: =Assumptions!B220 -> 3000 | F9: Prepaid insurance, software subscriptions
B10: Total Current Assets | C10: =SUM(C7:C9) -> 187974 | D10: =SUM(D7:D9) -> 410701.63 | E10: =SUM(E7:E9) -> 5178493.4
A11: Fixed Assets | B11: Computer Equipment | C11: 0 | D11: 0 | E11: 0 | F11: Simplified - included in operating expenses
A12: Fixed Assets | B12: Less: Accumulated Depreciation | C12: 0 | D12: 0 | E12: 0 | F12: 3-year straight line
B13: Net Fixed Assets | C13: =C11+C12 -> 0 | D13: =D11+D12 -> 0 | E13: =E11+E12 -> 0
A14: Intangible Assets | B14: Software Development (Capitalized) | C14: 0 | D14: 0 | E14: 0 | F14: Simplified - expensed rather than capitalized
A15: Intangible Assets | B15: Less: Amortization | C15: 0 | D15: 0 | E15: 0 | F15: 5-year amortization
B16: Net Intangible Assets | C16: =C14+C15 -> 0 | D16: =D14+D15 -> 0 | E16: =E14+E15 -> 0
B17: TOTAL ASSETS | C17: =C10+C13+C16 -> 187974 | D17: =D10+D13+D16 -> 410701.63 | E17: =E10+E13+E16 -> 5178493.4
B19: LIABILITIES
A20: Current Liabilities | B20: Accounts Payable | C20: 0 | D20: =IFERROR('Operating Expenses'!N56/2, "N/A") -> 12588.633 | E20: =IFERROR('Operating Expenses'!N56/2, "N/A") -> 12588.633 | F20: ~2 weeks of OpEx payable
A21: Current Liabilities | B21: Accrued Expenses | C21: 0 | D21: =Assumptions!B202 -> 5000 | E21: =Assumptions!B225 -> 8000 | F21: Accrued wages, payroll taxes, benefits
A22: Current Liabilities | B22: Deferred Revenue | C22: 0 | D22: ='P&L'!N29 -> 4485 | E22: ='P&L'!Z29 -> 71461 | F22: Prepaid monthly subscriptions (1 month)
B23: Total Current Liabilities | C23: =SUM(C20:C22) -> 0 | D23: =SUM(D20:D22) -> 22073.633 | E23: =SUM(E20:E22) -> 92049.633
A24: Long-term Liabilities | B24: Notes Payable | C24: 0 | D24: 0 | E24: 0 | F24: No debt assumed
B25: TOTAL LIABILITIES | C25: =C23+C24 -> 0 | D25: =D23+D24 -> 22073.633 | E25: =E23+E24 -> 92049.633
B27: EQUITY
A28: Equity | B28: Founder Investment | C28: ='Startup Costs-Led BuildWA'!B90 -> 187974 | D28: ='Startup Costs-Led BuildWA'!B90 -> 187974 | E28: ='Startup Costs-Led BuildWA'!B90 -> 187974 | F28: Initial capital
A29: Equity | B29: Retained Earnings | C29: 0 | D29: ='P&L'!B53 -> 418088.73 | E29: ='P&L'!B53+'P&L'!C53 -> 422991.23 | F29: Cumulative net profit from P&L
B30: TOTAL EQUITY | C30: =C28+C29 -> 187974 | D30: =D28+D29 -> 606062.73 | E30: =E28+E29 -> 610965.23
B32: TOTAL LIABILITIES + EQUITY | C32: =C25+C30 -> 187974 | D32: =D25+D30 -> 628136.37 | E32: =E25+E30 -> 703014.87
A34: CHECK | B34: Assets - (Liab + Equity) | C34: =C17-C32 -> 0 | D34: =D17-D32 -> -217434.73 | E34: =E17-E32 -> 4475478.6 | F34: Should be $0 (balanced)
A36: NOTE: Simplified cash-based balance sheet. Assets = Cash position from Cash Flow.
A37: Retained earnings = Change in cash from starting capital.
A38: KEY FINANCIAL RATIOS
A40: Ratio | B40: Start | C40: End Y1 | D40: End Y2 | E40: Notes
A41: Current Ratio | B41: =IFERROR(C10/C23, "N/A") -> N/A | C41: =IFERROR(D10/D23, "N/A") -> 18.605982 | D41: =IFERROR(E10/E23, "N/A") -> 56.257621 | E41: Current Assets / Current Liabilities (>1 is healthy)
A42: Debt-to-Equity | B42: =IFERROR(C25/C30, "N/A") -> 0 | C42: =IFERROR(D25/D30, "N/A") -> 0.036421367 | D42: =IFERROR(E25/E30, "N/A") -> 0.15066264 | E42: Total Liabilities / Equity (<1 is conservative)
A43: Cash Ratio | B43: =IFERROR(C7/C23, "N/A") -> N/A | C43: =IFERROR(D7/D23, "N/A") -> 18.144289 | D43: =IFERROR(E7/E23, "N/A") -> 54.807166 | E43: Cash / Current Liabilities (liquidity)
A44: ACCOUNTS RECEIVABLE / PAYABLE EXPLAINED
A46: Accounts Receivable (AR):
A47: - Money owed TO you by customers
A48: - Example: Carrier invoiced $1,200 for placement, pays in 30 days
A49: - Calculated as: ~1 month of revenue (30-day payment terms)
A51: Accounts Payable (AP):
A52: - Money YOU owe to vendors/suppliers
A53: - Example: GCP bill received, paid in 15 days
A54: - Calculated as: ~2 weeks of operating expenses
A56: Deferred Revenue:
A57: - Money received BEFORE service delivered
A58: - Example: Carrier prepays $299 monthly subscription
... A64: - This is why Cash Flow differs from Net Profit

Sheet Sources & Research
A1: VELOCITYMATCH PRO FORMA - SOURCES & RESEARCH DOCUMENTATION
A2: Research Conducted: December 22, 2025
A3: This document provides market research backing for all pricing decisions in this financial model.
A5: 1. TMS & FLEET MANAGEMENT SOFTWARE PRICING
A7: Source | B7: URL | C7: Key Finding | D7: Applied To
A8: Expert Market - Fleet Management Costs 2025 | B8: https://www.expertmarket.com/fleet-management/costs | C8: Fleet mgmt software: $20-150/vehicle/month; Entry-level ~$14/mo, mid-range $25-45/mo, premium $100+/mo | D8: Analytics & Telematics pricing tiers
A9: FreightWaves - Best Fleet Management Software | B9: https://ratings.freightwaves.com/best-fleet-management-software-systems/ | C9: Samsara: $30-40/vehicle; Motive: $25-35/vehicle; Matrack: $19.95/mo | D9: Analytics & Telematics per-truck benchmarks
A10: Truckpedia - Top TMS Software 2025 | B10: https://truckpedia.io/resources/top-7-tms-software-for-carriers-in-2025-and-how-to-choose | C10: Mid-market TMS: $233-$500+/month; Truckbase: $290/mo; Rose Rocket: $233/mo | D10: Matching Engine & Brokerage Automation pricing
A11: Trucking Dive - Top TMS 2025 | B11: https://www.truckingdive.com/spons/top-tms-software-for-carriers-in-2025-an-in-depth-review/724275/ | C11: Enterprise TMS (Turvo): $5,000+/month; McLeod/TMW for mega carriers | D11: Enterprise tier ceiling reference
A12: GPS Insight - Telematics Costs | B12: https://www.gpsinsight.com/blog/what-is-the-cost-of-telematics/ | C12: Hardware: $199-399/gateway; 5-15% fuel savings within 6 months; ROI in 3-9 months | D12: Telematics ROI messaging
A14: 2. DRIVER RECRUITING & HR TECH PRICING
A16: Source | B16: URL | C16: Key Finding | D16: Applied To
A17: People Managing People - Recruiting Software Pricing 2025 | B17: https://peoplemanagingpeople.com/recruitment/recruiting-software-pricing/ | C17: Small biz: $15-75/user/mo; Mid-market: $50-250/user/mo; Entry-level ATS: $1-25/user/mo | D17: Carrier HR Dashboard pricing
A18: Crozdesk - ATS Pricing Guide 2025 | B18: https://crozdesk.com/human-resources/applicant-tracking-ats-software/pricing | C18: Cloudrecruit: $65/user/mo; PC Recruiter: $85/user/mo; Crelate: $69/user/mo | D18: Per-seat pricing benchmarks
A19: AvatarFleet - Driver Compliance Software Cost | B19: https://www.avatarfleet.com/blog/how-much-does-driver-compliance-software-cost | C19: Compliance software: $150-$1,200/month ($1,800-$14,000 annually) | D19: Operations Automation (DQ files) pricing
A20: Tenstreet | B20: https://www.tenstreet.com/ | C20: Industry-leading driver recruitment software; private fleet solutions | D20: Competitive landscape reference
A21: Double Nickel | B21: https://www.getdoublenickel.com/ | C21: All-in-one truck driver recruiting software | D21: Feature comparison reference
A23: 3. JOB POSTING PLATFORM PRICING (Match Limit Benchmarks)
A25: Source | B25: URL | C25: Key Finding | D25: Applied To
A26: Indeed - Free vs Sponsored Jobs | B26: https://www.indeed.com/hire/resources/howtohub/free-vs-sponsored-jobs-on-indeed | C26: Free tier: 3 jobs/month (30 days each); Standard subscription: $120/mo; Professional: $300/mo | D26: Matching Engine - 10 matches/month baseline
A27: ZipRecruiter - Pricing | B27: https://www.ziprecruiter.com/plans | C27: Standard: $299-399/mo for 5 job slots; Premium: ~$519/mo; Pro: ~$899/mo | D27: Matching Engine $299/mo price point
A28: CareerBuilder/Monster Pricing | B28: https://hiring.careerbuilder.com/small-business-subscription-plans-and-pricing | C28: Monster+ Pro: $299/mo with resume database access; Legacy CB: $349-749/mo | D28: Matching Engine competitive positioning
A29: TrustRadius - ZipRecruiter Pricing 2025 | B29: https://www.trustradius.com/products/ziprecruiter/pricing | C29: Subscription model based on job slots, not per-post; can swap jobs as needed | D29: Match-based (not job-post) model validation
A31: 4. TRUCKING INDUSTRY DATA
A33: Source | B33: URL | C33: Key Finding | D33: Applied To
A34: ATA (American Trucking Associations) 2024 | B34: Industry Report | C34: 3.5 million CDL drivers in the US | D34: Market size assumptions
A35: ATRI (American Transportation Research Institute) 2024 | B35: Industry Report | C35: 94% annual driver turnover rate | D35: Market opportunity calculation (3.29M hires/year)
A36: Last Mile Campaign Data (Dec 2025) | B36: Internal Data | C36: Driver CAC: $16.28/lead; 35% conversion rate = $46.51 effective CAC | D36: Unit economics, COGS calculations
A38: 5. PRICING METHODOLOGY SUMMARY
A40: - Core Platform (Matching Engine): Priced at $299/mo to align with ZipRecruiter Standard tier and mid-market TMS solutions
A41: - Placement Services: Industry-standard recruiter placement fee at $1,200/hire with 94.6% contribution margin
A42: - Add-On Modules: Priced at 30-80% of core platform to encourage bundling while maintaining standalone value
A43: - Tiered Pricing (Telematics): Based on fleet management industry standard of $20-45/truck, consolidated into flat tiers for simplicity
A44: - Overage Pricing: Set at ~12% of full placement fee to encourage upgrade while providing flexibility
A45: - Target Market: Mid-market carriers (50-250 trucks) with average fleet size of 125 trucks
